{
 "file": "_STGSP1B.bin",
 "source_size": 25364,
 "built_size": 27479,
 "edits": [
  {
   "jp_offset": "0x1603",
   "jp_len": 15,
   "kind": "dialogue",
   "speaker": "用用用",
   "jp_text": "……ついに時が来ましたな",
   "zh_text": "……终于、等到这一刻了啊",
   "jp_hex": "150909f0ab34aa1cd9f0522a330000",
   "zh_hex": "150909e8e2e87902e826e7d7e7b9efb6e91fe7bae7c30000"
  },
  {
   "jp_offset": "0x163a",
   "jp_len": 9,
   "kind": "dialogue",
   "speaker": "用用用",
   "jp_text": "………………",
   "zh_text": "…………",
   "jp_hex": "150909090909090000",
   "zh_hex": "150909090900000000"
  },
  {
   "jp_offset": "0x166b",
   "jp_len": 23,
   "kind": "dialogue",
   "speaker": "用用用",
   "jp_text": "苦難の戦いの後、{00}ようやく手に入れた聞話……",
   "zh_text": "历经苦难的战斗之后、总算亲手换来的和{00}平……",
   "jp_hex": "15fe2a37b917379c0200f2a9ae34f2242af0f109090000",
   "zh_hex": "15e8fbe8b7e9e6e866e7b4ef28e7ffe7cde7fe02e881e889e894ef66ea78efcfe7b4e7d300e8870909000000"
  },
  {
   "jp_offset": "0x1682",
   "jp_len": 35,
   "kind": "dialogue",
   "speaker": "用用用",
   "jp_text": "……だが、問題は人励がそれを{00}手にできる程に成長しているか……",
   "zh_text": "……可问题在于、人类是否已成长到、足{00}以握住这份和平了呢……",
   "jp_hex": "150909f02702f1f138f0dc1cf0084c00ae34f01748e44f34f846232f17481b09090000",
   "zh_hex": "150909e7c4e997ea12ef29e87902efb2e841e7b6e9bbef3ae837ef34e7d702ea1e00e7f3eb37e859e7b9ea22e7d3e887e7bae907090900000000000000"
  },
  {
   "jp_offset": "0x16cd",
   "jp_len": 28,
   "kind": "dialogue",
   "speaker": "用用用",
   "jp_text": "……やはり私たちが橋えて{00}あげねばなりませんね、デキム",
   "zh_text": "……看来、还是得由我们来教导他们才行{00}呢、迪基姆",
   "jp_hex": "150909f11da8f0061cf1712f00f2b6363933473d274d3602f6760000",
   "zh_hex": "150909e7f6efcf02e7f7e7b6e80ae8a6efcce7bbefcfeaacea4be80ce7bbe836efd600e90702ea11e829e8230000000000"
  },
  {
   "jp_offset": "0x173c",
   "jp_len": 14,
   "kind": "dialogue",
   "speaker": "迪基姆·巴顿",
   "jp_text": "その通りです、マリーメイアさま",
   "zh_text": "正是如此、玛莉梅雅大人",
   "jp_hex": "15f00df0f8302502f13df0380000",
   "zh_hex": "15ef3be7b6e7f0e7ca02e845e81ee9f2ebfdefa5efb2000000000000"
  },
  {
   "jp_offset": "0x179d",
   "jp_len": 29,
   "kind": "dialogue",
   "speaker": "玛莉梅雅",
   "jp_text": "……お父さまから預かった{00}クリスマスプレゼント……",
   "zh_text": "……这是父亲大人托付给我的圣诞礼物…{00}…",
   "jp_hex": "1509091ae510f0381b46f6a12d2a00f272f4c47683e066856b09090000",
   "zh_hex": "150909e7b9e7b6e888e894efa5efb2e7f4e97ee839efcce7b4e90ded06eb65e99e0900090000000000"
  },
  {
   "jp_offset": "0x17ba",
   "jp_len": 15,
   "kind": "dialogue",
   "speaker": "玛莉梅雅",
   "jp_text": "ちゃんとみんなに届けなくてはね",
   "zh_text": "得好好地送到大家手里才行呢",
   "jp_hex": "15f5ebf12434ffacf0432ff2610000",
   "zh_hex": "15e80ae7c7e7c7ef63e9bae7d7efa5e7dfef66ef31e836efd6e9070000"
  },
  {
   "jp_offset": "0x17c9",
   "jp_len": 8,
   "kind": "dialogue",
   "speaker": "玛莉梅雅",
   "jp_text": "ふふふ……",
   "zh_text": "呵呵呵……",
   "jp_hex": "153a3a3a09090000",
   "zh_hex": "15ef3def3def3d09090000"
  },
  {
   "jp_offset": "0x17e8",
   "jp_len": 9,
   "kind": "dialogue",
   "speaker": "联邦兵",
   "jp_text": "たっ、隊長！",
   "zh_text": "队、队长！",
   "jp_hex": "152a2d02f104060000",
   "zh_hex": "15e7c902e7c9ef34ef97000000"
  },
  {
   "jp_offset": "0x1805",
   "jp_len": 11,
   "kind": "dialogue",
   "speaker": "联邦兵",
   "jp_text": "うわぁぁぁっ！！",
   "zh_text": "哇啊啊啊！！",
   "jp_hex": "15184b1515152d06060000",
   "zh_hex": "15ea88e7c3e7c3e7c3ef97ef970000"
  },
  {
   "jp_offset": "0x185d",
   "jp_len": 17,
   "kind": "dialogue",
   "speaker": "联邦兵",
   "jp_text": "くっ！{00}こいつら、いったい……！？",
   "zh_text": "唔！这帮家伙、到底是什么来头……！？",
   "jp_hex": "151e2d0600f1d64602f0fe090906050000",
   "zh_hex": "15e81def97e7b9e910e7dfe7fd02e7d7e9b4e7b6e7dde7bdefcfe92e0909ef9705000000"
  },
  {
   "jp_offset": "0x1893",
   "jp_len": 19,
   "kind": "dialogue",
   "speaker": "玛莉梅雅兵",
   "jp_text": "無能力者の時代は終わったのだ！！",
   "zh_text": "无能之辈的时代、已经结束了！！",
   "jp_hex": "15f801daad37f1e638f06a2d2a372b06060000",
   "zh_hex": "15e7dce7c6e7cded0ce7b4ef2de8e702ef3ae8b7e868e895e7baef97ef97000000"
  },
  {
   "jp_offset": "0x1911",
   "jp_len": 12,
   "kind": "dialogue",
   "speaker": "玛琉",
   "jp_text": "……OZの決起！？",
   "zh_text": "……是OZ起兵了吗！？",
   "jp_hex": "150909f07137f54d06050000",
   "zh_hex": "150909e7b6ed1ceedae847ef93e7bae802ef97050000"
  },
  {
   "jp_offset": "0x1938",
   "jp_len": 30,
   "kind": "dialogue",
   "speaker": "蕾蒂·安",
   "jp_text": "去OZの急進破が決起し、{00}連邦の主要施設を占挙……",
   "zh_text": "前OZ的激进派发动了兵变、占领了联邦{00}的主要设施……",
   "jp_hex": "15e179f07137fe20e4b71cf54d230200f01e37fcc4f42e4cf84809090000",
   "zh_hex": "15ef51ed1ceedae7b4e9b9e892e985e870ef30e7baef93e95502eb51ea20e7baef2eefaa00e7b4e954ef2aeb43eb8d0909000000"
  },
  {
   "jp_offset": "0x1956",
   "jp_len": 32,
   "kind": "dialogue",
   "speaker": "蕾蒂·安",
   "jp_text": "……畳包部は桜知すらできなかった{00}完全にしてやられた径だ",
   "zh_text": "……情报部竟然连一点征兆都没察觉、完{00}全是被人摆了一道",
   "jp_hex": "150909f153cc38f83b2546f017f0772d2a00f17334232f4346492ae1bf2b0000",
   "zh_hex": "150909e88be913ef70ef2ce7efe86eefb6e822ecd2eddde840e7d8ea8be8ae02e87e00efb4e7b6e7f1efb2eb8be7baefb6e82a00000000"
  },
  {
   "jp_offset": "0x1991",
   "jp_len": 16,
   "kind": "dialogue",
   "speaker": "玛琉",
   "jp_text": "では、私たちプリベンターは……",
   "zh_text": "那么、我们预防者该……",
   "jp_hex": "15f00a02a8f006f2b7f2d13809090000",
   "zh_hex": "15e7b7e7bd02efcce7bbea5ae968ef6ee8980909000000"
  },
  {
   "jp_offset": "0x19bc",
   "jp_len": 28,
   "kind": "dialogue",
   "speaker": "蕾蒂·安",
   "jp_text": "現在、畳包部が決起軍についての{00}畳包を収集している",
   "zh_text": "目前、情报部正在收集有关叛军的情报",
   "jp_hex": "15f14102f153cc1cf54d9834f0ab2f3700f1534cfe4a232f17480000",
   "zh_hex": "15efd4ef5102e88be913ef70ef3bef29e926ea98e7cbe8bbef43e7e0e7b4e88be91300000000"
  },
  {
   "jp_offset": "0x19d8",
   "jp_len": 18,
   "kind": "dialogue",
   "speaker": "蕾蒂·安",
   "jp_text": "首暴者の位置が判明次第……",
   "zh_text": "一旦查明主谋的位置……",
   "jp_hex": "15e2c3e55fad37f5241cf40cf22f09090000",
   "zh_hex": "15efb6ebcdeae9ef39e954ea6ee7b4e834ea0e09090000"
  },
  {
   "jp_offset": "0x1a19",
   "jp_len": 10,
   "kind": "dialogue",
   "speaker": "米莉亚莉亚·哈乌",
   "jp_text": "かっ、艦長！！",
   "zh_text": "舰、舰长！！",
   "jp_hex": "151b2d02f03406060000",
   "zh_hex": "15e7d402e7d4ef34ef97ef97000000"
  },
  {
   "jp_offset": "0x1a3e",
   "jp_len": 9,
   "kind": "dialogue",
   "speaker": "玛琉",
   "jp_text": "どうしたの！？",
   "zh_text": "怎么了！？",
   "jp_hex": "15f07f2a3706050000",
   "zh_hex": "15e7f2e7bde7baef97050000"
  },
  {
   "jp_offset": "0x1a62",
   "jp_len": 15,
   "kind": "dialogue",
   "speaker": "米莉亚莉亚·哈乌",
   "jp_text": "今、モニターに映します！",
   "zh_text": "这就投到屏幕上！",
   "jp_hex": "15a202fd640834e0b4f01225060000",
   "zh_hex": "15e7b9e7c5e948e7d7ed4eec14ef4cef97000000"
  },
  {
   "jp_offset": "0x1a88",
   "jp_len": 28,
   "kind": "dialogue",
   "speaker": "玛莉梅雅",
   "jp_text": "私は世界国家元首の正騰なる継昇者{00}マリーメイア·クシュリナーダ…",
   "zh_text": "我乃世界国家元首的正统继承人、玛莉梅{00}雅·克休里那达……",
   "jp_hex": "15a838f0c0f503ff4437ff793348e1c7e302ad00f13d04f221090000",
   "zh_hex": "15efccefdde83ce8f5efc4e7dfecaeef40e7b4ef3be929e9d6ea75efb202e845e81ee9f200ebfdef4be7d5e90eef31e7b7ef2b0909000000"
  },
  {
   "jp_offset": "0x1aa4",
   "jp_len": 17,
   "kind": "dialogue",
   "speaker": "玛莉梅雅",
   "jp_text": "トレーズ·クシュリナーダの{00}娘であります",
   "zh_text": "也就是特列斯·克休里那达之女",
   "jp_hex": "15f0a104f2213700e58130f046f0250000",
   "zh_hex": "15e7c0e7c5e7b6e7cfe8b5e7c8ef4be7d5e90eef31e7b7ef2be7cdefad00000000000000"
  },
  {
   "jp_offset": "0x1ab5",
   "jp_len": 38,
   "kind": "dialogue",
   "speaker": "玛莉梅雅",
   "jp_text": "……私は父の違志を継ぎます{00}人は戦ってこそ意議ある存在なのです！",
   "zh_text": "……我要继承父亲的遗志、人唯有不断战{00}斗、才是有意义的存在！",
   "jp_hex": "150909a838e51037f6224ce1c7e04ff02500b438b92d2ff065f7d9f00ff11233373025060000",
   "zh_hex": "150909efccef2ae9d6ea75e888e894e7b4eba9ea1802efb2ea89e7cbe7b5e982ef2800e7ff02e836e7b6e7cbef3ce8cee7b4e993ef29ef97000000000000"
  },
  {
   "jp_offset": "0x1af2",
   "jp_len": 29,
   "kind": "dialogue",
   "speaker": "巴尔特菲尔德",
   "jp_text": "トレーズ·クシュリナーダの娘か……{00}また、えらいものが出てきたな",
   "zh_text": "特列斯·克休里那达的女儿吗……这下又{00}冒出个了不得的人物啊",
   "jp_hex": "15f0a104f22137e5811b090900f09e02f90ff17f371caf2ff074330000",
   "zh_hex": "15e7cfe8b5e7c8ef4be7d5e90eef31e7b7ef2be7b4efadeb7ce8020909e7b9ef4de8f100eb7fefbee828e7bae7b5e80ae7b4efb2e99ee7c3000000000000"
  },
  {
   "jp_offset": "0x1b2a",
   "jp_len": 9,
   "kind": "dialogue",
   "speaker": "玛琉",
   "jp_text": "………………",
   "zh_text": "…………",
   "jp_hex": "150909090909090000",
   "zh_hex": "150909090900000000"
  },
  {
   "jp_offset": "0x1b4e",
   "jp_len": 16,
   "kind": "dialogue",
   "speaker": "拉克丝·克莱因",
   "jp_text": "……事態は申刻なようですね",
   "zh_text": "……看来事态相当严重呢",
   "jp_hex": "150909f30038f93233f0073025360000",
   "zh_hex": "150909e7f6efcfefb8e994e8b1ef53eaa1e8a1e907000000"
  },
  {
   "jp_offset": "0x1b79",
   "jp_len": 29,
   "kind": "dialogue",
   "speaker": "蕾蒂·安",
   "jp_text": "……突然の決起に正規軍は{00}体勢を立て直すので手一杯だ",
   "zh_text": "……面对突如其来的兵变、正规军光是重{00}整阵脚就已忙得不可开交",
   "jp_hex": "150909f8c537f54d34f3c0983800f4af4cf271e438253730fa9c2b0000",
   "zh_hex": "150909e862e7bee8b6e7f0e8cfefcfe7b4ef93e95502ef3bea42e7e0e83de7b6e8a100e9feeb48eb68e7c5ef3aea06e80ae7b5e7c4e7fae8610000000000"
  },
  {
   "jp_offset": "0x1bb1",
   "jp_len": 24,
   "kind": "dialogue",
   "speaker": "狄安娜·索瑞露",
   "jp_text": "では、私どもの力が{00}再び必要となるのですね",
   "zh_text": "这么说来、又要用到我们的力量了呢",
   "jp_hex": "15f00a02a8f0cd37da1c00f2f4f0b5313348373025360000",
   "zh_hex": "15e7b9e7bde7edefcf02e8f1ef2aefb3e7d7efcce7bbe7b4efb0e851e7bae9070000000000"
  },
  {
   "jp_offset": "0x1be4",
   "jp_len": 28,
   "kind": "dialogue",
   "speaker": "蕾蒂·安",
   "jp_text": "先ほどの通信で決起軍本隊の位置も{00}遠からず判明する",
   "zh_text": "凭刚才那段通讯、叛军主力的位置不久也{00}会查明",
   "jp_hex": "15b8f09537f1b430f54dfd7237f5244100e0c51b4626f40cf0040000",
   "zh_hex": "15ea49e8bce836e7b7ea6bef59eb1b02ef43e7e0e954efb0e7b4e834ea0ee7b5e9dbe7c000e7e2eae9ef3900000000"
  },
  {
   "jp_offset": "0x1c00",
   "jp_len": 35,
   "kind": "dialogue",
   "speaker": "蕾蒂·安",
   "jp_text": "君たちには敵中枢に進撃してもらい、{00}これ以上の事態各大を防いで……",
   "zh_text": "希望你们能向敌方中枢挺进、阻止事态进{00}一步扩大……",
   "jp_hex": "1597f0063438c3f5b334f8af232ff040170200f0ee37f300f6bc4ce560173009090000",
   "zh_hex": "15e87be965e7b8e7bbe7c6efc1e7e3efb1ef4eec75eb5ce89202e8efe869efb8e994e89200efb6ea93ec1aefa509090000"
  },
  {
   "jp_offset": "0x1c3e",
   "jp_len": 23,
   "kind": "dialogue",
   "speaker": "巴尔特菲尔德",
   "jp_text": "……いや{00}そう{SLOT:2133}長にしている時間はないな",
   "zh_text": "……不、已经没有慢慢来的工夫了",
   "jp_hex": "150909f06000f009f9cb34232f1748f13ff03a17330000",
   "zh_hex": "150909e7b502ef3ae8b7e7d8e7cbe979e979efcfe7b4eae4e830e7ba0000000000"
  },
  {
   "jp_offset": "0x1c70",
   "jp_len": 10,
   "kind": "dialogue",
   "speaker": "蕾蒂·安",
   "jp_text": "バルトフェルドどの？",
   "zh_text": "巴尔特菲尔德先生？",
   "jp_hex": "15f8e6f901f542050000",
   "zh_hex": "15e85be7e1e7cfea6ce7e1e82cef8bef8d050000"
  },
  {
   "jp_offset": "0x1cc4",
   "jp_len": 17,
   "kind": "dialogue",
   "speaker": "米莉亚莉亚·哈乌",
   "jp_text": "所属不明のモビルスーツ軍、接近中！",
   "zh_text": "一支所属不明的MS部队、正在接近！",
   "jp_hex": "15f270f1e337f081e1b702f2e9c0060000",
   "zh_hex": "15efb6e883e7fbea24e7b5ef39e7b4efa7ef9eef70e7c902ef3bef29efceefd8ef9700000000"
  },
  {
   "jp_offset": "0x1cf0",
   "jp_len": 7,
   "kind": "dialogue",
   "speaker": "蕾蒂·安",
   "jp_text": "な……！",
   "zh_text": "什么……！",
   "jp_hex": "15330909060000",
   "zh_hex": "15e7dde7bd0909ef970000"
  },
  {
   "jp_offset": "0x1d12",
   "jp_len": 37,
   "kind": "dialogue",
   "speaker": "巴尔特菲尔德",
   "jp_text": "遊撃戦力である我々を放置しておくほど{00}敵もバカではないと言うことさ",
   "zh_text": "敌人也没蠢到、会放着我们这支游击战力{00}不管",
   "jp_hex": "15e5ae99f07d30f00ff0184cf2b1232f1a1ef09500c341f0cef00a3317319b18f002220000",
   "zh_hex": "15e7e3efb2e7c0e7d8e94be7d702e7e2e86ce86defcce7bbe7b9e883ea94e7ccef28efb000e7b5e93b0000000000"
  },
  {
   "jp_offset": "0x1d41",
   "jp_len": 10,
   "kind": "dialogue",
   "speaker": "巴尔特菲尔德",
   "jp_text": "……ラミアス艦長！",
   "zh_text": "……拉米亚斯舰长！",
   "jp_hex": "150909f0ecf034060000",
   "zh_hex": "150909e7c2e878e7d6e7c8e7d4ef34ef97000000"
  },
  {
   "jp_offset": "0x1d66",
   "jp_len": 6,
   "kind": "dialogue",
   "speaker": "玛琉",
   "jp_text": "ええ！",
   "zh_text": "嗯！",
   "jp_hex": "15f05a060000",
   "zh_hex": "15e865ef970000"
  },
  {
   "jp_offset": "0x1d76",
   "jp_len": 26,
   "kind": "dialogue",
   "speaker": "玛琉",
   "jp_text": "全艦、攻撃体勢に移行！！{00}敵MSを迎撃します！",
   "zh_text": "全舰、转入攻击态势！！迎击敌方MS！",
   "jp_hex": "15f11a02f01ff4af34f546060600c3f02c4cf10df01225060000",
   "zh_hex": "15efb4e7d402e9c2e891ef67e7cce994e8fdef97ef97e931e7cce7e3efb1efa7ef9eef970000000000"
  },
  {
   "jp_offset": "0x1da7",
   "jp_len": 11,
   "kind": "dialogue",
   "speaker": "贝拉·罗纳",
   "jp_text": "あれが決起軍……",
   "zh_text": "那就是叛军吗……",
   "jp_hex": "15f0301cf54d9809090000",
   "zh_hex": "15e7b7e7c5e7b6ef43e7e0e80209090000"
  },
  {
   "jp_offset": "0x1dd7",
   "jp_len": 29,
   "kind": "dialogue",
   "speaker": "玛琉",
   "jp_text": "総員、ただちに迎撃体勢を！{00}プリベンター全艦、戦闘開始！",
   "zh_text": "全员、立即进入迎击态势！预防者全舰、{00}开始战斗！",
   "jp_hex": "15f14602f0442c34f10df4af4c0600f2b7f2d1f11a02f04ff0b1060000",
   "zh_hex": "15efb4e84902e86be855e892e891e931e7cce994e8fdef97ea5ae968ef6eefb4e7d40200e7fae908ef28e7ffef97000000000000"
  },
  {
   "jp_offset": "0x1e19",
   "jp_len": 21,
   "kind": "dialogue",
   "speaker": "マリーメイア国我",
   "jp_text": "くっ……！{00}プリベンターの力がこれほどとは！",
   "zh_text": "唔……！预防者的实力、竟有这么强！",
   "jp_hex": "151e2d09090600f2b7f2d137da1cf4213138060000",
   "zh_hex": "15e81d0909ef97ea5ae968ef6ee7b4e87fefb002ef2ce7cbe7b9e7bde8adef97000000"
  },
  {
   "jp_offset": "0x1e2e",
   "jp_len": 25,
   "kind": "dialogue",
   "speaker": "マリーメイア国我",
   "jp_text": "こうなっては{00}戦力を出し惜しみしていられん！",
   "zh_text": "事到如今、再也不能保留战力了！",
   "jp_hex": "15f087332d2f3800f07d4caf23f3223e232f1746494d060000",
   "zh_hex": "15efb8e7d7e7f0efb902e80be7c0e7b5e7c6ea47e98cef28efb0e7baef970000000000"
  },
  {
   "jp_offset": "0x1e47",
   "jp_len": 13,
   "kind": "dialogue",
   "speaker": "マリーメイア国我",
   "jp_text": "麗の部隊を出せ！！",
   "zh_text": "出动那支部队！！",
   "jp_hex": "15e5e837f0644caf2706060000",
   "zh_hex": "15efbeef30e7b7e883ef70e7c9ef97ef9700000000"
  },
  {
   "jp_offset": "0x1e86",
   "jp_len": 10,
   "kind": "dialogue",
   "speaker": "玛琉",
   "jp_text": "あれは……！！",
   "zh_text": "那是……！！",
   "jp_hex": "15f03038090906060000",
   "zh_hex": "15e7b7e7b60909ef97ef970000"
  },
  {
   "jp_offset": "0x1ec2",
   "jp_len": 11,
   "kind": "dialogue",
   "speaker": "夸特罗·巴吉纳",
   "jp_text": "抜かったな……！",
   "zh_text": "大意了……！",
   "jp_hex": "15f7fc2d2a330909060000",
   "zh_hex": "15efa5ef3ce7ba0909ef97000000"
  },
  {
   "jp_offset": "0x1ecd",
   "jp_len": 31,
   "kind": "dialogue",
   "speaker": "夸特罗·巴吉纳",
   "jp_text": "元OZだけにブルーコスモスとの{00}{SLOT:1813}がりもあるということか！",
   "zh_text": "毕竟是前OZ、原来和蓝色宇宙也有勾结{00}吗！",
   "jp_hex": "15e1eff0712b1f34f304f1db61313700fb914741f00f311718f0021b060000",
   "zh_hex": "15ea2cef2ce7b6ef51ed1ceeda02e8e4efcfe7d3eaf1e89fe8bee8bfe7c0e7cbecb7e86800e802ef9700000000"
  },
  {
   "jp_offset": "0x1f18",
   "jp_len": 19,
   "kind": "dialogue",
   "speaker": "マリーメイア国我",
   "jp_text": "よーし！{00}このまま一気にプリベンターを……",
   "zh_text": "好！就这样一口气、把预防者……",
   "jp_hex": "154508230600f080f1d1f2b7f2d14c09090000",
   "zh_hex": "15e7c7ef97e7c5e7b9e7daefb6eabde8ed02e81bea5ae968ef6e09090000000000"
  },
  {
   "jp_offset": "0x1f50",
   "jp_len": 7,
   "kind": "dialogue",
   "speaker": "マリーメイア国我",
   "jp_text": "なっ！？",
   "zh_text": "什么！？",
   "jp_hex": "15332d06050000",
   "zh_hex": "15e7dde7bdef97050000"
  },
  {
   "jp_offset": "0x1f89",
   "jp_len": 16,
   "kind": "dialogue",
   "speaker": "用用用",
   "jp_text": "トレーズの訪劣が現れた以上……",
   "zh_text": "既然特列斯的亡灵已经现身……",
   "jp_hex": "15f0a137f9c11cf14d2af0e209090000",
   "zh_hex": "15e8c4e7efe7cfe8b5e7c8e7b4ebb2eaebef3ae8b7e82fe88d09090000"
  },
  {
   "jp_offset": "0x1fa9",
   "jp_len": 26,
   "kind": "dialogue",
   "speaker": "用用用",
   "jp_text": "おとなしく敢桶で民っているわけには{00}いかんのでな",
   "zh_text": "我可没法乖乖地、就此长眠不起啊",
   "jp_hex": "15f64b1eff2a30e57d2d2f1748f050343800171b4d3730330000",
   "zh_hex": "15efcce7c4e7d8e84ee9a3e9a3ef6302e7c5e7caef34ed8fe7b5e847e7c3000000"
  },
  {
   "jp_offset": "0x1fe8",
   "jp_len": 19,
   "kind": "dialogue",
   "speaker": "用用用",
   "jp_text": "プリベンターのマリュー·ラミアス{00}艦長ですね",
   "zh_text": "您就是预防者的玛琉·拉米亚斯舰长吧",
   "jp_hex": "15f2b7f2d137f1ad04f0ec00f0343025360000",
   "zh_hex": "15e835e7c5e7b6ea5ae968ef6ee7b4e845ead2ef4be7c2e878e7d6e7c8e7d4ef34e7d0000000"
  },
  {
   "jp_offset": "0x2016",
   "jp_len": 10,
   "kind": "dialogue",
   "speaker": "玛琉",
   "jp_text": "あ、貴方は……",
   "zh_text": "啊、您是……",
   "jp_hex": "151602f02f3809090000",
   "zh_hex": "15e7c302e835e7b60909000000"
  },
  {
   "jp_offset": "0x203b",
   "jp_len": 15,
   "kind": "dialogue",
   "speaker": "用用用",
   "jp_text": "さしずめ火消しの風……",
   "zh_text": "说到底、我也不过是一阵灭火之风罢了…{00}…",
   "jp_hex": "15f5f32640fb7bf2ace51a09090000",
   "zh_hex": "15e7ede7d7e9b402efcce7c0e7b5ef36e7b6efb6eb48e8e1e8dae7cdeb75eaefe7ba09000900000000"
  },
  {
   "jp_offset": "0x204a",
   "jp_len": 27,
   "kind": "dialogue",
   "speaker": "用用用",
   "jp_text": "プリベンター·ウィンドとでも{00}名乗らせていただきましょうか",
   "zh_text": "就请允许我、自称为预防者·风吧",
   "jp_hex": "15f2b7f2d104fdb831f01b00f2b246272ff125f0d12344f0c80000",
   "zh_hex": "15e7c5e83aecade8a7efcc02efb5ea01e7c1ea5ae968ef6eef4beb75e7d00000000000000000"
  },
  {
   "jp_offset": "0x2080",
   "jp_len": 13,
   "kind": "dialogue",
   "speaker": "玛琉",
   "jp_text": "プリベンター…ウィンド……？",
   "zh_text": "预防者……风……？",
   "jp_hex": "15f2b7f2d109fdb80909050000",
   "zh_hex": "15ea5ae968ef6e0909eb750909050000"
  },
  {
   "jp_offset": "0x20a8",
   "jp_len": 31,
   "kind": "dialogue",
   "speaker": "卡迭吉娜",
   "jp_text": "完全聞話を願う一兵士として{00}貴方がたに除力させていただく！",
   "zh_text": "作为一名渴望完全和平的士兵、就让我来{00}助你们一臂之力！",
   "jp_hex": "15f173f0f14ce13f18fc4ea5f02800f02ff12234f38cf02e2ff1251e060000",
   "zh_hex": "15ef2fe7c1efb6e8aced84e965e87eefb4e7d3e887e7b4ef64ef9302e7c5e7f9efccefcf00ea23e7b8e7bbefb6ee92e7cdefb0ef97000000000000"
  },
  {
   "jp_offset": "0x20ec",
   "jp_len": 26,
   "kind": "dialogue",
   "speaker": "露克蕾琪娅·诺茵",
   "jp_text": "ゼクス……生きていたのですね{00}私は信じていました",
   "zh_text": "杰克斯……您果然还活着、我一直都坚信{00}着",
   "jp_hex": "15f1080909f0882ff0133730253600a838f1032ff029232a0000",
   "zh_hex": "15e8ebe7d5e7c80909e835e871e7efe7f7e8d4e86d02efccefb6e875e840eb80e90f00e86d000000"
  },
  {
   "jp_offset": "0x2121",
   "jp_len": 19,
   "kind": "dialogue",
   "speaker": "卡迭吉娜",
   "jp_text": "……ノインか{00}オマエには苦漏をかける",
   "zh_text": "……是诺茵吗、又要让你为我操劳了",
   "jp_hex": "150909f34a1b00f06c3438f7404cf0f0480000",
   "zh_hex": "150909e7b6e972e971e80202e8f1ef2ae7f9e7b8e7c1efcceac7ec4ae7ba00000000"
  },
  {
   "jp_offset": "0x214f",
   "jp_len": 17,
   "kind": "dialogue",
   "speaker": "露克蕾琪娅·诺茵",
   "jp_text": "もう、貴方の側を離れません",
   "zh_text": "我再也不会离开您的身边了",
   "jp_hex": "15f02a02f02f37e3c44cf21e3d274d0000",
   "zh_hex": "15efcce80be7c0e7b5e7e2e901e7fae835e7b4e88de899e7ba0000"
  },
  {
   "jp_offset": "0x2160",
   "jp_len": 27,
   "kind": "dialogue",
   "speaker": "露克蕾琪娅·诺茵",
   "jp_text": "ずっと、待っていたんです{00}もう待つのはごめんです",
   "zh_text": "我一直、一直在等着您、再也不想这样等{00}下去了",
   "jp_hex": "15f1d702e3e22d2ff0134d302500f02ae3e2f2e438f30330250000",
   "zh_hex": "15efccefb6e87502efb6e875ef29e826e86de83502e80be7c0e7b5e7e6e7b9e7dae82600ef4de7ebe7ba0000000000"
  },
  {
   "jp_offset": "0x2196",
   "jp_len": 15,
   "kind": "dialogue",
   "speaker": "卡迭吉娜",
   "jp_text": "良いのか……こんな私で？",
   "zh_text": "你真的愿意吗……跟着我这样的人？",
   "jp_hex": "15e5df17371b0909f04aa830050000",
   "zh_hex": "15e7b8e820e7b4e961ef3ce8020909e973e86defcce7b9e7dae7b4efb205000000"
  },
  {
   "jp_offset": "0x21c0",
   "jp_len": 13,
   "kind": "dialogue",
   "speaker": "露克蕾琪娅·诺茵",
   "jp_text": "そんな貴方だから……です",
   "zh_text": "正因为是这样的您……",
   "jp_hex": "15f026f02ff047090930250000",
   "zh_hex": "15ef3bef33e7c1e7b6e7b9e7dae7b4e8350909000000"
  },
  {
   "jp_offset": "0x21e8",
   "jp_len": 8,
   "kind": "dialogue",
   "speaker": "卡迭吉娜",
   "jp_text": "……そうか",
   "zh_text": "……是吗",
   "jp_hex": "150909f0091b0000",
   "zh_hex": "150909e7b6e8020000"
  },
  {
   "jp_offset": "0x220b",
   "jp_len": 12,
   "kind": "dialogue",
   "speaker": "卡迭吉娜",
   "jp_text": "では行くぞ、ノイン！",
   "zh_text": "那么、我们走吧、诺茵！",
   "jp_hex": "15f00a9f1e2902f34a060000",
   "zh_hex": "15e7b7e7bd02efcce7bbe890e7d002e972e971ef970000"
  },
  {
   "jp_offset": "0x2238",
   "jp_len": 9,
   "kind": "dialogue",
   "speaker": "露克蕾琪娅·诺茵",
   "jp_text": "はい、ゼクス！",
   "zh_text": "好的、杰克斯！",
   "jp_hex": "15f01602f108060000",
   "zh_hex": "15e7c7e7b402e8ebe7d5e7c8ef97000000"
  },
  {
   "jp_offset": "0x2266",
   "jp_len": 14,
   "kind": "dialogue",
   "speaker": "贝拉·罗纳",
   "jp_text": "……終わったようですね",
   "zh_text": "……似乎已经结束了呢",
   "jp_hex": "150909f06a2d2af0073025360000",
   "zh_hex": "150909e944e933ef3ae8b7e868e895e7bae9070000"
  },
  {
   "jp_offset": "0x2299",
   "jp_len": 36,
   "kind": "dialogue",
   "speaker": "巴尔特菲尔德",
   "jp_text": "既にプリベンターにまで手を打っていた{00}とは……容易ならざる相手だな",
   "zh_text": "竟然连预防者都已被暗中下了手……真不{00}是个好对付的对手啊",
   "jp_hex": "15f187f2b7f2d134f02bae4ce3dd2d2ff0130031380909f8d73346e05248f05f2b330000",
   "zh_hex": "15ef2ce7efe86eea5ae968ef6ee840ef3ae7f1ea6aef4eef4de7baef660909e820e7b500e7b6e828e7c7e7bee97ee7b4e7beef66e7c30000000000"
  },
  {
   "jp_offset": "0x22e2",
   "jp_len": 7,
   "kind": "dialogue",
   "speaker": "蕾蒂·安",
   "jp_text": "マリーメイア……",
   "zh_text": "玛莉梅雅……",
   "jp_hex": "15f13d09090000",
   "zh_hex": "15e845e81ee9f2ebfd09090000"
  },
  {
   "jp_offset": "0x22e9",
   "jp_len": 16,
   "kind": "dialogue",
   "speaker": "蕾蒂·安",
   "jp_text": "トレーズさまのご息女とは……",
   "zh_text": "竟是特列斯大人的千金……",
   "jp_hex": "15f0a1f03837e051fb0d313809090000",
   "zh_hex": "15ef2ce7b6e7cfe8b5e7c8efa5efb2e7b4eafde902090900000000"
  },
  {
   "jp_offset": "0x22f9",
   "jp_len": 9,
   "kind": "dialogue",
   "speaker": "蕾蒂·安",
   "jp_text": "………………",
   "zh_text": "…………",
   "jp_hex": "150909090909090000",
   "zh_hex": "150909090900000000"
  },
  {
   "jp_offset": "0x2319",
   "jp_len": 10,
   "kind": "dialogue",
   "speaker": "マリーメイア国我",
   "jp_text": "第一ケート部鎖！",
   "zh_text": "封锁第一道门！",
   "jp_hex": "15f20af9d7fd1c060000",
   "zh_hex": "15eb83ebfae940efb6e82ae90cef970000"
  },
  {
   "jp_offset": "0x233e",
   "jp_len": 25,
   "kind": "dialogue",
   "speaker": "玛莉梅雅兵",
   "jp_text": "第匂から第{SLOT:1818}、{00}続いてケート部鎖します！",
   "zh_text": "接着封锁第二到第六道门！",
   "jp_hex": "15f35d1b46e3ede63a0200e3d0172ff9d7fd1cf01225060000",
   "zh_hex": "15efcee86deb83ebfae940ea13e7d7e940eddfe82ae90cef97000000000000000000"
  },
  {
   "jp_offset": "0x23ae",
   "jp_len": 9,
   "kind": "dialogue",
   "speaker": "莉莉娜",
   "jp_text": "………………",
   "zh_text": "…………",
   "jp_hex": "150909090909090000",
   "zh_hex": "150909090900000000"
  },
  {
   "jp_offset": "0x23f7",
   "jp_len": 15,
   "kind": "dialogue",
   "speaker": "玛莉梅雅",
   "jp_text": "……不思吉に思いませんか？",
   "zh_text": "……不觉得奇怪吗？",
   "jp_hex": "150909f64a34a6f029274d1b050000",
   "zh_hex": "150909e7b5e8aee80ae904ea07e802050000"
  },
  {
   "jp_offset": "0x2406",
   "jp_len": 32,
   "kind": "dialogue",
   "speaker": "玛莉梅雅",
   "jp_text": "兵器のない聞話な世界に何戸こんな{00}シェルターが必要なのでしょう？",
   "zh_text": "在一个没有兵器的和平世界里、为何还需{00}要这样的避难所呢？",
   "jp_hex": "15f14c373317f0f133f0c034f3aaf04a00f6e8081cf0b5333730234418050000",
   "zh_hex": "15ef29efb6e828e7d8e7cbef93e8c3e7b4e7d3e887e83ce8f5ef3102e7c1efbce7f7e92d00ef2ae7b9e7dae7b4efd9e866e7fbe9070500000000"
  },
  {
   "jp_offset": "0x2441",
   "jp_len": 9,
   "kind": "dialogue",
   "speaker": "莉莉娜",
   "jp_text": "………………",
   "zh_text": "…………",
   "jp_hex": "150909090909090000",
   "zh_hex": "150909090900000000"
  },
  {
   "jp_offset": "0x2465",
   "jp_len": 34,
   "kind": "dialogue",
   "speaker": "玛莉梅雅",
   "jp_text": "麗えるなら裂史というものは{00}終わらないワルツのようなものです",
   "zh_text": "若要打个比方、历史就如同一曲永不停歇{00}的华尔兹",
   "jp_hex": "15fa7a483346f3d9311718f0193800f06a463317e075826837f00733f01930250000",
   "zh_hex": "15e7e7ef2ae7f5e828e825efb102e8fbe925e7c5e7f0e85defb6ece2e9bfe7b5e934ee4500e7b4ed2ce7e1e856000000000000"
  },
  {
   "jp_offset": "0x2487",
   "jp_len": 28,
   "kind": "dialogue",
   "speaker": "玛莉梅雅",
   "jp_text": "戦争、聞話、角命の三拍子が{00}いつまでも続く……",
   "zh_text": "战争、和平、革命这三拍子、将永无止境{00}地周而复始……",
   "jp_hex": "15f07002f0f102fc6537e271e4c6e2841c00f26e41e3d01e09090000",
   "zh_hex": "15ef28e85202e7d3e88702edc5e853e7b9eaa0e804e88602e84ae9bfe7dce869eb8100ef63ea5ce89ce9eee9080909000000"
  },
  {
   "jp_offset": "0x24be",
   "jp_len": 18,
   "kind": "dialogue",
   "speaker": "莉莉娜",
   "jp_text": "何をするつもりなのです、アナタは？",
   "zh_text": "你究竟想做什么？",
   "jp_hex": "158a4cf004f08b3337302502f08238050000",
   "zh_hex": "15e7b8e906ef2ce7e6e81ce7dde7bd050000"
  },
  {
   "jp_offset": "0x24eb",
   "jp_len": 15,
   "kind": "dialogue",
   "speaker": "玛莉梅雅",
   "jp_text": "私にひざまずかせるのです",
   "zh_text": "让他们、统统向我下跪",
   "jp_hex": "15a834fef3f15b1b27483730250000",
   "zh_hex": "15e7f9e80ce7bb02e929e929efc1efccef4deff30000000000"
  },
  {
   "jp_offset": "0x24fa",
   "jp_len": 11,
   "kind": "dialogue",
   "speaker": "玛莉梅雅",
   "jp_text": "……全ての人励を",
   "zh_text": "……这世上所有的人类",
   "jp_hex": "150909f07c37f0dc4c0000",
   "zh_hex": "150909e7b9e83cef4ce7fbe7cbe7b4efb2e84100000000"
  },
  {
   "jp_offset": "0x2520",
   "jp_len": 6,
   "kind": "dialogue",
   "speaker": "莉莉娜",
   "jp_text": "っ！？",
   "zh_text": "唔……！？",
   "jp_hex": "152d06050000",
   "zh_hex": "15e81d0909ef9705000000"
  },
  {
   "jp_offset": "0x2541",
   "jp_len": 32,
   "kind": "dialogue",
   "speaker": "玛莉梅雅",
   "jp_text": "そう、私の戴寒によって{00}人励は新しい時代を迎えるのです",
   "zh_text": "没错、随着我的登基、人类将迎来一个全{00}新的时代",
   "jp_hex": "15f00902a837e3e5e11c34452d2f00f0dc38f40a17f1e64cf292483730250000",
   "zh_hex": "15e7d8e88502e9a1e86defcce7b4e9a0e82902efb2e841e84ae931efcfefb6e828efb400ef8ae7b4ef2de8e7000000000000"
  },
  {
   "jp_offset": "0x2561",
   "jp_len": 29,
   "kind": "dialogue",
   "speaker": "玛莉梅雅",
   "jp_text": "リリーナ·ビースクラフト、貴女には{00}その手伝いをしていただきます",
   "zh_text": "莉莉娜·匹斯克拉福特、就请你来协助我{00}完成这件事",
   "jp_hex": "15f17e04f1e1f26902f10c343800f00df27f174c232ff125f0d1250000",
   "zh_hex": "15e81ee81ee7eaef4bed2ae7c8e7d5e7c2ea7ce7cf02e7c5e83ae7b8efcfe8f6ea23efcc00e87ee837e7b9e991efb8000000000000"
  },
  {
   "jp_offset": "0x2599",
   "jp_len": 9,
   "kind": "dialogue",
   "speaker": "莉莉娜",
   "jp_text": "……手伝い？",
   "zh_text": "……协助？",
   "jp_hex": "150909f27f17050000",
   "zh_hex": "150909e8f6ea23050000"
  },
  {
   "jp_offset": "0x25bd",
   "jp_len": 25,
   "kind": "dialogue",
   "speaker": "玛莉梅雅",
   "jp_text": "去サンクキングダムの女王にして、{00}現、次官……",
   "zh_text": "你身为前桑克王国的女王、如今又是现任{00}次官……",
   "jp_hex": "15e179f2e6f35737f07934232f0200e1f5f6f9f44209090000",
   "zh_hex": "15e7b8e88de7c1ef51ea2be7d5e884efc4e7b4efade88402e7f0efb9e8f1e7b6e82fe89a00e864ef920909000000"
  },
  {
   "jp_offset": "0x25d6",
   "jp_len": 34,
   "kind": "dialogue",
   "speaker": "玛莉梅雅",
   "jp_text": "一時期はデルマイユ公の後押しを受け{00}世界国家の代表もつとめた……",
   "zh_text": "一度还在迪尔麦优公爵的扶持下、出任过{00}世界国家的代表……",
   "jp_hex": "15f3cee14f38fddfe212379cf82b4cf0c200f0c0f50337f2c6412ef4fb2a09090000",
   "zh_hex": "15efb6e96de7f7ef29ea11e7e1ec43e9afe9a4ef19e7b4eecee9efef4d02efbee89aef3600e83ce8f5efc4e7dfe7b4e8e7e9e70909000000"
  },
  {
   "jp_offset": "0x25f8",
   "jp_len": 36,
   "kind": "dialogue",
   "speaker": "玛莉梅雅",
   "jp_text": "その貴女が世界の代表として{00}この私に地球圏の最高位を委ねるのです",
   "zh_text": "就由你以世界代表的身份、把地球圈的最{00}高之位托付给我",
   "jp_hex": "15f00df10c1cf0c037f2c6f02800f005a834f010e1db37f744e08c4cfa0b483730250000",
   "zh_hex": "15e7c5e8a6e7b8e7f3e83ce8f5e8e7e9e7e7b4e88dea2202e81bef63efd3e9fbe7b4e8c500e812e7cde834e7f4e97ee839efcc000000"
  },
  {
   "jp_offset": "0x2637",
   "jp_len": 10,
   "kind": "dialogue",
   "speaker": "莉莉娜",
   "jp_text": "そのために私を……",
   "zh_text": "你抓我来、就是为了这个……",
   "jp_hex": "15f1dc34a84c09090000",
   "zh_hex": "15e7b8e962efccefcf02e7c5e7b6e7c1e7bae7b9e82809090000"
  },
  {
   "jp_offset": "0x265c",
   "jp_len": 7,
   "kind": "dialogue",
   "speaker": "玛莉梅雅",
   "jp_text": "うふふ……",
   "zh_text": "呵呵呵……",
   "jp_hex": "15f7ab09090000",
   "zh_hex": "15ef3def3def3d09090000"
  },
  {
   "jp_offset": "0x2663",
   "jp_len": 37,
   "kind": "dialogue",
   "speaker": "玛莉梅雅",
   "jp_text": "貴女の権限は貴女が思っている以上に{00}強い影響力を持っているのですわ",
   "zh_text": "你手中的权限、远比你自己所想的、拥有{00}更强的影响力",
   "jp_hex": "15f10c37fc9038f10c1ca62d2f1748f0e23400f2b8f5a1da4ce29e2d2f17483730254b0000",
   "zh_hex": "15e7b8ef66ef4ee7b4eb39eb2302e94ce825e7b8efb5e8c9e7fbe7e6e7b402eb35e7cb00e952e8ade7b4ea8eecbfefb000000000000000"
  },
  {
   "jp_offset": "0x269f",
   "jp_len": 11,
   "kind": "dialogue",
   "speaker": "玛琉",
   "jp_text": "ブリュッセル大騰領府……",
   "zh_text": "布鲁塞尔总统府……",
   "jp_hex": "15fc1bf76ce50b09090000",
   "zh_hex": "15e831e8a2e950e7e1e881e929ea6009090000"
  },
  {
   "jp_offset": "0x26c5",
   "jp_len": 24,
   "kind": "dialogue",
   "speaker": "蕾蒂·安",
   "jp_text": "現在判明した畳包によれば{00}マリーメイア·クシュリナーダは……",
   "zh_text": "根据目前查明的情报、玛莉梅雅·克休里{00}那达她……",
   "jp_hex": "15f141f40c232af1533445493900f13d04f2213809090000",
   "zh_hex": "15e9b8e8ccefd4ef51eae9ef39e7b4e88be91302e845e81ee9f2ebfdef4be7d5e90eef3100e7b7ef2be88e090900000000"
  },
  {
   "jp_offset": "0x26dd",
   "jp_len": 31,
   "kind": "dialogue",
   "speaker": "蕾蒂·安",
   "jp_text": "ドーリアン、次官とともに{00}大騰領府のシェルターにこもっている",
   "zh_text": "正和多利安次官一起、躲在总统府的避难{00}所里",
   "jp_hex": "15f7d5f7d785f6f9f44231f2b400f76ce50b37f6e8083421412d2f17480000",
   "zh_hex": "15ef3be7d3e7e9e82ee7fce864ef92efb6e84702ea6fef29e881e929ea60e7b4efd9e86600e7fbef3100000000"
  },
  {
   "jp_offset": "0x2717",
   "jp_len": 9,
   "kind": "dialogue",
   "speaker": "希罗·尤伊",
   "jp_text": "………………",
   "zh_text": "…………",
   "jp_hex": "150909090909090000",
   "zh_hex": "150909090900000000"
  },
  {
   "jp_offset": "0x273b",
   "jp_len": 30,
   "kind": "dialogue",
   "speaker": "巴尔特菲尔德",
   "jp_text": "周囲はOZのMSによって{00}睡も籠らさぬ警備豆か……",
   "zh_text": "四周被OZ的MS团团围住、守得水泄不{00}通……",
   "jp_hex": "15f83f38f07137f02c34452d2f00e34d41ffde2235f897e3481b09090000",
   "zh_hex": "15eb52ea5ce7f1ed1ceedae7b4efa7ef9eea5eea5ee9dee85902e8a8e80aebd4ed7ee7b500ef590909000000"
  },
  {
   "jp_offset": "0x2759",
   "jp_len": 27,
   "kind": "dialogue",
   "speaker": "巴尔特菲尔德",
   "jp_text": "しかも、正規軍は対応におおわらわで{00}まともに動けない",
   "zh_text": "况且、正规军正手忙脚乱地应对、根本动{00}弹不得",
   "jp_hex": "15f61202f3c09838f57f34f2334b464b3000f8df34c6f170170000",
   "zh_hex": "15e8d0e99902ef3bea42e7e0ef3bef66ea06eb68e976ef63e873e7be02e9b8efa6ef3000e946e7b5e80a00000000"
  },
  {
   "jp_offset": "0x278f",
   "jp_len": 29,
   "kind": "dialogue",
   "speaker": "蕾蒂·安",
   "jp_text": "おそらく、現在動けるのは{00}君たちをおいて他にいないだろう",
   "zh_text": "眼下能够行动的、恐怕除了你们之外再无{00}他人了",
   "jp_hex": "15f20602f141c61f4837380097f0064cf186e3d8341733172b4a180000",
   "zh_hex": "15e90bef4de7c6e920efd6ef30e7b402eb33e958e974e7bae7b8e7bbe7cde8f7e80be7dc00e80cefb2e7ba000000"
  },
  {
   "jp_offset": "0x27c7",
   "jp_len": 9,
   "kind": "dialogue",
   "speaker": "玛琉",
   "jp_text": "………………",
   "zh_text": "…………",
   "jp_hex": "150909090909090000",
   "zh_hex": "150909090900000000"
  },
  {
   "jp_offset": "0x27d0",
   "jp_len": 28,
   "kind": "dialogue",
   "speaker": "玛琉",
   "jp_text": "マリーメイア軍中枢の撃破と{00}ドーリアン、次官の救出ですね",
   "zh_text": "也就是击破玛莉梅雅军的中枢、并救出多{00}利安次官、对吧",
   "jp_hex": "15f13d98f5b337f0693100f7d5f7d785f6f9f44237f3683025360000",
   "zh_hex": "15e7c0e7c5e7b6e7ccef6de845e81ee9f2ebfde7e0e7b4ef4eec7502e957e8caefbee7e900e82ee7fce864ef9202e7bee7d000000000"
  },
  {
   "jp_offset": "0x27ec",
   "jp_len": 32,
   "kind": "dialogue",
   "speaker": "玛琉",
   "jp_text": "……忍務、了解しました{00}ただちに現地へ向かわせてもらいます",
   "zh_text": "……任务、我明白了、我们这就赶往现场",
   "jp_hex": "150909f1f002f086f012232a00f0442c34fa263bf0584b272ff040f029250000",
   "zh_hex": "150909e89ae94f02efccef39e809e7ba02efcce7bbe7b9e7c5ea04e911e82fe8760000000000"
  },
  {
   "jp_offset": "0x2827",
   "jp_len": 36,
   "kind": "dialogue",
   "speaker": "蕾蒂·安",
   "jp_text": "危険な忍務なのは昇知しているが{00}今となっては君たちが頼みの綱だ",
   "zh_text": "我也知道这是项危险的任务、可如今、你{00}们就是我们唯一的指望了",
   "jp_hex": "15f11333f1f0333738f23d232f17481c00a231332d2f3897f0061ce5c03e37e22c2b0000",
   "zh_hex": "15efcce7c0e85ae82ae7b9e7b6eec5e935e932e7b4e89ae94f02e7c4e7f0efb902e7b800e7bbe7c5e7b6efcce7bbea89efb6e7b4e8c0e965e7ba000000000000"
  },
  {
   "jp_offset": "0x284b",
   "jp_len": 10,
   "kind": "dialogue",
   "speaker": "蕾蒂·安",
   "jp_text": "……頼んだぞ",
   "zh_text": "……拜托你们了",
   "jp_hex": "150909e5c04d2b290000",
   "zh_hex": "150909e91ae7f4e7b8e7bbe7ba0000"
  },
  {
   "jp_offset": "0x286c",
   "jp_len": 18,
   "kind": "dialogue",
   "speaker": "米莉亚莉亚·哈乌",
   "jp_text": "艦長！{00}進路上にレーダー反応！！",
   "zh_text": "舰长！前进航线上出现雷达反应！！",
   "jp_hex": "15f0340600f23eb234f4f508f16f06060000",
   "zh_hex": "15e7d4ef34ef97ef51e892e9c1e916ef4cefbee82fe8afef2be87ce873ef97ef97000000"
  },
  {
   "jp_offset": "0x287e",
   "jp_len": 12,
   "kind": "dialogue",
   "speaker": "米莉亚莉亚·哈乌",
   "jp_text": "ザフトの戦艦です！！",
   "zh_text": "是扎夫特的战舰！！",
   "jp_hex": "15f03f37f15e302506060000",
   "zh_hex": "15e7b6e84be830e7cfe7b4ef28e7d4ef97ef970000"
  },
  {
   "jp_offset": "0x28a5",
   "jp_len": 13,
   "kind": "dialogue",
   "speaker": "玛琉",
   "jp_text": "……ザフトですって！？",
   "zh_text": "……你说扎夫特！？",
   "jp_hex": "150909f03f30252d2f06050000",
   "zh_hex": "150909e7b8e7ede84be830e7cfef9705000000"
  },
  {
   "jp_offset": "0x28c9",
   "jp_len": 12,
   "kind": "dialogue",
   "speaker": "玛琉",
   "jp_text": "私たちに叫力……？",
   "zh_text": "是要协助我们……？",
   "jp_hex": "15a8f00634f13a0909050000",
   "zh_hex": "15e7b6ef2ae8f6ea23efcce7bb0909050000"
  },
  {
   "jp_offset": "0x28f0",
   "jp_len": 7,
   "kind": "dialogue",
   "speaker": "ザフト国我",
   "jp_text": "……はい",
   "zh_text": "……是",
   "jp_hex": "150909f0160000",
   "zh_hex": "150909e7b60000"
  },
  {
   "jp_offset": "0x28f7",
   "jp_len": 30,
   "kind": "dialogue",
   "speaker": "ザフト国我",
   "jp_text": "今回のOZ残凍軍の決起については{00}我々プラントも憂両しています",
   "zh_text": "对于这次OZ残党军的兵变、我们普兰特{00}也深感忧虑",
   "jp_hex": "15f2a537f071f4739837f54d34f41000f018f0d041fd36232ff029250000",
   "zh_hex": "15e7bee879e7b9e864ed1ceedae97bea73e7e0e7b4ef93e95502efcce7bbe838e86fe7cf00e7c0eb0de87dee1deba100000000"
  },
  {
   "jp_offset": "0x2915",
   "jp_len": 34,
   "kind": "dialogue",
   "speaker": "ザフト国我",
   "jp_text": "可能ならばザフトも軍に叫力して{00}事態の収拾をはかりたいのですが……",
   "zh_text": "可以的话、扎夫特也想出兵协助、设法收{00}拾这个局面、可是……",
   "jp_hex": "15f169334639f03f419834f13a232f00f30037f7464cf4a0472a1737f07209090000",
   "zh_hex": "15e7c4e7f3e7b4e81f02e84be830e7cfe7c0e7e6efbeef93e8f6ea2302eb43e84ee92600eae6e7b9e828ea8ce86202e7c4e7b6090900000000000000"
  },
  {
   "jp_offset": "0x2937",
   "jp_len": 30,
   "kind": "dialogue",
   "speaker": "ザフト国我",
   "jp_text": "連邦との蒸約もあって{00}自由に軍を動かすことはできません",
   "zh_text": "碍于与联邦之间的条约、我们无法自由调{00}动军队",
   "jp_hex": "15f01e3137f70741f04c2f00f6c734984cf1e725f00238f0173d274d0000",
   "zh_hex": "15e8c6e879e832ef2eefaae7cde8fce7b4e9d4e9ac02efcce7bbe7dce84eefb5e8a6e95c00ef30e7e0e7c900000000000000"
  },
  {
   "jp_offset": "0x297a",
   "jp_len": 15,
   "kind": "dialogue",
   "speaker": "玛利根",
   "jp_text": "それで我々に援除をすると？",
   "zh_text": "所以、是要支援我们吗？",
   "jp_hex": "15f00830f01834f88a4cf0f9050000",
   "zh_hex": "15e7fbe7f302e7b6ef2ae883e863efcce7bbe80205000000"
  },
  {
   "jp_offset": "0x29a4",
   "jp_len": 31,
   "kind": "dialogue",
   "speaker": "ザフト国我",
   "jp_text": "ZGMF+X23S、セイバー……{00}我々ザフトの最新鋭機です",
   "zh_text": "ZGMF-X23S、救世主高达……是{00}我们扎夫特的最新锐机体",
   "jp_hex": "15faa9e00ef72cfc20026350f1a3090900f018f03f37f57ae0b99230250000",
   "zh_hex": "15eedaeed1efa7eca5ef71eed9ef5fef60ef9e02e8cae83ce954e812ef2b0909e7b600efcce7bbe84be830e7cfe7b4e8c5ef8aed14e7e4ef4f000000000000"
  },
  {
   "jp_offset": "0x29c3",
   "jp_len": 29,
   "kind": "dialogue",
   "speaker": "ザフト国我",
   "jp_text": "これを貴方がたプリベンターに{00}提侠させていただきたい",
   "zh_text": "我们希望、能把它提供给你们预防者",
   "jp_hex": "15f00e4cf02ff122f2b7fa0564e0043400f69af02e2ff125f074170000",
   "zh_hex": "15efcce7bbe87be96502e7c6e81be978e821eca9e839e7b8e7bbea5ae968ef6e0000000000"
  },
  {
   "jp_offset": "0x29fb",
   "jp_len": 16,
   "kind": "dialogue",
   "speaker": "玛利根",
   "jp_text": "ザフトの最新鋭機を我々に？",
   "zh_text": "扎夫特的最新锐机、要给我们？",
   "jp_hex": "15f03f37f57ae0b9924cf01834050000",
   "zh_hex": "15e84be830e7cfe7b4e8c5ef8aed14e7e402ef2ae839efcce7bb050000"
  },
  {
   "jp_offset": "0x2a26",
   "jp_len": 38,
   "kind": "dialogue",
   "speaker": "ザフト国我",
   "jp_text": "デュランダル吉長から貴艦に可能な限り{00}援除をするようにと真し付かっています",
   "zh_text": "杜兰朵议长下过指示、要我们尽一切可能{00}支援贵舰",
   "jp_hex": "15fdeef1ac1b46fc7134f16933e1f74700f88a4cf004f0073431e33923e506f3b6f029250000",
   "zh_hex": "15e8cbe86fef94e8e3ef34ef4def36e8c0eab002ef2aefcce7bbe8f2efb6ef3fe7c4e7c600e883e863e930e7d40000000000"
  },
  {
   "jp_offset": "0x2a67",
   "jp_len": 9,
   "kind": "dialogue",
   "speaker": "玛利根",
   "jp_text": "む、だが……",
   "zh_text": "唔、可是……",
   "jp_hex": "153f02f02709090000",
   "zh_hex": "15e81d02e7c4e7b609090000"
  },
  {
   "jp_offset": "0x2a8b",
   "jp_len": 22,
   "kind": "dialogue",
   "speaker": "玛琉",
   "jp_text": "……セイバーというのですね{00}そのモビルスーツは",
   "zh_text": "……那台MS、就叫救世主高达是吧",
   "jp_hex": "1509096350f1a33117183730253600f00df081380000",
   "zh_hex": "150909e7b7ea16efa7ef9e02e7c5e8c1e8cae83ce954e812ef2be7b6e7d000000000"
  },
  {
   "jp_offset": "0x2abc",
   "jp_len": 10,
   "kind": "dialogue",
   "speaker": "玛利根",
   "jp_text": "……ラミアス艦長？",
   "zh_text": "……舰长？",
   "jp_hex": "150909f0ecf034050000",
   "zh_hex": "150909e7d4ef34050000"
  },
  {
   "jp_offset": "0x2ae1",
   "jp_len": 20,
   "kind": "dialogue",
   "speaker": "玛琉",
   "jp_text": "今は一刻を争う事態です{00}クワトロ大尉",
   "zh_text": "如今正是分秒必争的关头、克瓦特罗大尉",
   "jp_hex": "15a238f5254ce3b318f300302500f073f05d0000",
   "zh_hex": "15e7f0efb9ef3be7b6efaeee79e860e852e7b4e8bbe92e02e7d5e99fe7cfe7ecefa5efc60000000000"
  },
  {
   "jp_offset": "0x2af5",
   "jp_len": 26,
   "kind": "dialogue",
   "speaker": "玛琉",
   "jp_text": "それに、戦力は少しでも多い方が{00}安心できるわ",
   "zh_text": "再说、战力哪怕多上一分、也能让人更安{00}心",
   "jp_hex": "15f0083402f07d38f106f01be3d917d01c00f359f017484b0000",
   "zh_hex": "15e80be7ed02ef28efb0e8ffe958e7e9ef4cefb6efae02e7c0e7c6e7f9efb2e952e7fc00e82d0000000000000000"
  },
  {
   "jp_offset": "0x2b2a",
   "jp_len": 7,
   "kind": "dialogue",
   "speaker": "ザフト国我",
   "jp_text": "では……",
   "zh_text": "那么……",
   "jp_hex": "15f00a09090000",
   "zh_hex": "15e7b7e7bd09090000"
  },
  {
   "jp_offset": "0x2b4c",
   "jp_len": 27,
   "kind": "dialogue",
   "speaker": "玛琉",
   "jp_text": "デュランダル吉長のご好意、{00}ありがたく受けさせていただきます",
   "zh_text": "杜兰朵议长的这份好意、我们就感激地收{00}下了",
   "jp_hex": "15fdeef1ac37e051fa2a0200f3621ef0c2f02e2ff125f0d1250000",
   "zh_hex": "15e8cbe86fef94e8e3ef34e7b4e7b9ea22e7c7ef3c02efcce7bbe7c5e87de9b9ef63e92600ef4de7ba0000000000"
  },
  {
   "jp_offset": "0x5bda",
   "jp_len": 14,
   "kind": "dialogue",
   "speaker": "玛琉·拉米亚斯",
   "jp_text": "こ、ここまでだなんて……",
   "zh_text": "竟、竟然就到此为止了……",
   "jp_hex": "152102f03ef02b2bf06609090000",
   "zh_hex": "15ef2c02ef2ce7efe7c5e7d7e7cae7c1e869e7ba09090000"
  },
  {
   "jp_offset": "0x5c66",
   "jp_len": 13,
   "kind": "dialogue",
   "speaker": "布莱特·诺亚",
   "jp_text": "これまでの戦い、ご苦漏",
   "zh_text": "这一路征战、辛苦你了",
   "jp_hex": "15f00ef02b37b91702f6420000",
   "zh_hex": "15e7b9efb6e8d2ecd2ef2802ea58e9e6e7b8e7ba0000"
  },
  {
   "jp_offset": "0x5c73",
   "jp_len": 32,
   "kind": "dialogue",
   "speaker": "布莱特·诺亚",
   "jp_text": "この「宇宙世紀ルート」を最後まで{00}遊んでくれて感射する",
   "zh_text": "感谢你将这条『宇宙世纪路线』一路游玩{00}到了最后",
   "jp_hex": "15f005e00bf0a8f695fb35e00c4cf145f02b00e5ae4d30f0152ff288f0040000",
   "zh_hex": "15e87de8b2e7b8e84ae7b9e9d40ce8bee8bfe83ceb99e8d2e9160defb6e8d2ea94e97000e7d7e7bae8c5e7fe000000"
  },
  {
   "jp_offset": "0x5c93",
   "jp_len": 31,
   "kind": "dialogue",
   "speaker": "布莱特·诺亚",
   "jp_text": "なお、ロンド·ベル隊の戦いは{00}ここでひとまず終了するが……",
   "zh_text": "另外、隆德·贝尔队的征战、就先在此告{00}一段落了……",
   "jp_hex": "15f29002f17a04f0f4bd37b9173800f03e30f9fcf15bf3aef0041c09090000",
   "zh_hex": "15e99be8f702ed16e82cef4be857e7e1e7c9e7b4ecd2ef2802e7c5ef8bef29e7cae8e500efb6ea6be92ae7ba0909000000"
  },
  {
   "jp_offset": "0x5cb2",
   "jp_len": 37,
   "kind": "dialogue",
   "speaker": "布莱特·诺亚",
   "jp_text": "ケーム自体はまだ続けることが可能だ{00}この後も引き続きを楽しんで雷しい",
   "zh_text": "不过游戏本身仍可继续下去、今后也请你{00}继续尽情游玩",
   "jp_hex": "15f763f702f0ea2bf13048f0021cf1692b00f0059c41f429e3d01d4cf5d64d30f252170000",
   "zh_hex": "15e7b5ef36ea94ea3eefa6e88deab9e7c4e9d6e9adef4de7eb02efb9e7fee7c0e83ae7b800e9d6e9ade8f2e88bea94e97000000000"
  },
  {
   "jp_offset": "0x5cd7",
   "jp_len": 39,
   "kind": "dialogue",
   "speaker": "布莱特·诺亚",
   "jp_text": "また、本ルートを最後まで遊んでくれた{00}君には特別ステージも用意されている",
   "zh_text": "另外、为一路通关本路线的你、还特意准{00}备了一个特别关卡",
   "jp_hex": "15f09e02d2fb354cf145f02be5ae4d30f0152a00973438e490e534f43841f21622492f17480000",
   "zh_hex": "15e99be8f702e7c1efb6e8d2ef59e8bbefa6e8d2e916e7b4e7b802e7f7e7cfef3ce87a00e877e7baefb6e828e7cfe7e5e8bbe8010000000000000000"
  },
  {
   "jp_offset": "0x5cfe",
   "jp_len": 33,
   "kind": "dialogue",
   "speaker": "布莱特·诺亚",
   "jp_text": "我々とは別に戦いを続けていた{00}アークエンジェル隊との特別演習だ",
   "zh_text": "那是与我们分头作战至今的大天使队之间{00}的特别演习",
   "jp_hex": "15f0183138e53434b9174cf1302ff01300f093f09abd3137e490e534f4722b0000",
   "zh_hex": "15e7b7e7b6e832efcce7bbefaee92eef2fef28e897efb9e7b4efa5e844e83fe7c9e7cde8fc00e7b4e7cfe7e5ea2feab600000000"
  },
  {
   "jp_offset": "0x5d1f",
   "jp_len": 37,
   "kind": "dialogue",
   "speaker": "布莱特·诺亚",
   "jp_text": "彼らと戦い、君が育ててきた部隊の{00}強さを確かめてみるのも良いだろう",
   "zh_text": "和他们交手一番、亲自检验你培养至今的{00}部队实力、也是件好事",
   "jp_hex": "15f0d531b91702971cfb702ff074f0643700e18c224cf4972f3e483741e5df172b4a180000",
   "zh_hex": "15e7d3e80ce7bbe861ef66efb6ee6d02e894efb5ee40ea99e7b8edfeec0be897efb9e7b400ef70e7c9e87fefb002e7c0e7b6e991e7c7efb80000000000000000"
  },
  {
   "jp_offset": "0x5d44",
   "jp_len": 37,
   "kind": "dialogue",
   "speaker": "布莱特·诺亚",
   "jp_text": "フリーバトルで「特殊演習」を{00}選ぶことで彼らと戦うことができる",
   "zh_text": "在自由对战中选择『特殊演习』、便能与{00}他们一决高下",
   "jp_hex": "15f33071f3cd30e00bf0a3f472e00c4c00e39ae05af00230f0d531b918f0021cf017480000",
   "zh_hex": "15ef29efb5e8a6e7beef28ef4ee966eaaa0ce7cfed7bea2feab60d02e8fae7c6e83200e80ce7bbefb6e8abe812ef4d00000000"
  },
  {
   "jp_offset": "0x5d69",
   "jp_len": 36,
   "kind": "dialogue",
   "speaker": "布莱特·诺亚",
   "jp_text": "…では、「SDガンダム{00}{01}{01}{01}{01}{01}GジェネレーシユンDS」",
   "zh_text": "……那么、就请继续游玩『SD高达G世{00}代DS』吧",
   "jp_hex": "1509f00a02e00b1411f041f048000101010101e020f9786f83085fe073851114e00c0000",
   "zh_hex": "150909e7b7e7bd02e7c5e83ae9d6e9adea94e9700cef9eef96e812ef2beed1e83c00e8e7ef96ef9e0de7d00000"
  },
  {
   "jp_offset": "0x5d8d",
   "jp_len": 21,
   "kind": "dialogue",
   "speaker": "布莱特·诺亚",
   "jp_text": "この先も最後まで{00}じっくり楽しんでほしい",
   "zh_text": "今后也希望你能静下心来、尽情玩到最后",
   "jp_hex": "15f005b841f145f02b00fed0f5d64d30f238170000",
   "zh_hex": "15efb9e7fee7c0e87be965e7b8e7c6eab3ef4de82defcf02e8f2e88be970e7d7e8c5e7fe00000000"
  },
  {
   "jp_offset": "0x5e06",
   "jp_len": 31,
   "kind": "dialogue",
   "speaker": "玛琉",
   "jp_text": "ここまで私のような頼りない艦長に{00}付き合ってくれて、ありがとう",
   "zh_text": "谢谢你一路以来、一直陪着我这个不太靠{00}得住的舰长",
   "jp_hex": "15f03ef02ba837f00733e5c0473317f0343400f3c92d2ff0152f02f1340000",
   "zh_hex": "15e8b2e8b2e7b8efb6e8d2e7f3efcf02efb6e875ef42e86defcce7b9e828e7b5e86ae8c700e80ae859e7b4e7d4ef3400000000"
  },
  {
   "jp_offset": "0x5e25",
   "jp_len": 30,
   "kind": "dialogue",
   "speaker": "玛琉",
   "jp_text": "この「聞成ガンダムルート」は{00}ここで終了となります",
   "zh_text": "这条『平成高达路线』、就到此告一段落{00}了",
   "jp_hex": "15f005e00be52ce361f041f048fb35e00c3800f03e30f3aef395f0250000",
   "zh_hex": "15e7b9e9d40ce887e837e812ef2be8d2e9160d02e7c5e7d7e7cae8e5efb6ea6be92a00e7ba000000000000"
  },
  {
   "jp_offset": "0x5e43",
   "jp_len": 26,
   "kind": "dialogue",
   "speaker": "玛琉",
   "jp_text": "もっとも、私たちプリベンターの{00}戦いは終わったけど……",
   "zh_text": "虽说、我们预防者的这场战斗、是已经结{00}束了……",
   "jp_hex": "15f39a02a8f006f2b7f2d13700b91738f06a2df51f3209090000",
   "zh_hex": "15e8b8e7ed02efcce7bbea5ae968ef6ee7b4e7b9e876ef28e7ff02e7b6ef3ae8b7e86800e895e7ba090900000000"
  },
  {
   "jp_offset": "0x5e5d",
   "jp_len": 38,
   "kind": "dialogue",
   "speaker": "玛琉",
   "jp_text": "…ケーム自体はまだ続けることも可能よ{00}この後も引き続きケームを楽しんでね",
   "zh_text": "……不过游戏本身也还能继续下去哦、今{00}后也请你继续享受游戏吧",
   "jp_hex": "1509f763f702f0ea2bf13048f00241f1694500f0059c41f429e3d01df7634cf5d64d30360000",
   "zh_hex": "150909e7b5ef36ea94ea3eefa6e88de7c0e7f7e7c6e9d6e9adef4de7ebe91902efb900e7fee7c0e83ae7b8e9d6e9adec06e8c8ea94ea3ee7d00000000000"
  },
  {
   "jp_offset": "0x5e83",
   "jp_len": 36,
   "kind": "dialogue",
   "speaker": "玛琉",
   "jp_text": "最後までこのルートを遊んでくれた君に{00}新しいステージも用意されているわ",
   "zh_text": "为一路玩通这条路线的你、还另外准备了{00}全新的关卡哦",
   "jp_hex": "15f145f02bf005fb354ce5ae4d30f0152a973400f40a17f43841f21622492f17484b0000",
   "zh_hex": "15e7c1efb6e8d2e970ef59e7b9e9d4e8d2e916e7b4e7b802e7f7e99be8f7e87ae877e7ba00efb4ef8ae7b4e8bbe801e9190000000000"
  },
  {
   "jp_offset": "0x5ea7",
   "jp_len": 27,
   "kind": "dialogue",
   "speaker": "玛琉",
   "jp_text": "私たちとは別にティターンズや{00}ネオ·ジオンと戦っていた…",
   "zh_text": "那是与我们分头、和提坦斯及新吉翁交过{00}手的……",
   "jp_hex": "15a8f0063138e53434f0354300f02004f00c31b92d2ff013090000",
   "zh_hex": "15e7b7e7b6e832efcce7bbefaee92e02e7d3e821e843e7c8e9cfef8ae7d9ee88e861ef3600ef66e7b40909000000"
  },
  {
   "jp_offset": "0x5ec2",
   "jp_len": 19,
   "kind": "dialogue",
   "speaker": "玛琉",
   "jp_text": "…ロンド·ベル隊との特別演習よ",
   "zh_text": "……正是和那支隆德·贝尔队之间的特别{00}演习哦",
   "jp_hex": "1509f17a04f0f4bd3137e490e534f472450000",
   "zh_hex": "150909ef3be7b6e7d3e7b7e883ed16e82cef4be857e7e1e7c9e7cde8fce7b4e7cfe7e500ea2feab6e9190000"
  },
  {
   "jp_offset": "0x5ed5",
   "jp_len": 38,
   "kind": "dialogue",
   "speaker": "玛琉",
   "jp_text": "フリーバトルで「特別演習」を選ぶと{00}彼らと戦うことができるわ",
   "zh_text": "在自由对战中选择『特别演习』、就能和{00}他们一战了哦",
   "jp_hex": "15f33071f3cd30e00be490e534f472e00c4ce39ae05a3100f0d531b918f0021cf017484b0000",
   "zh_hex": "15ef29efb5e8a6e7beef28ef4ee966eaaa0ce7cfe7e5ea2feab60d02e7c5e7c6e7d300e80ce7bbefb6ef28e7bae9190000"
  },
  {
   "jp_offset": "0x5efb",
   "jp_len": 14,
   "kind": "dialogue",
   "speaker": "玛琉",
   "jp_text": "ぜひ、挑戦してみてね",
   "zh_text": "请你一定要去挑战看看哦",
   "jp_hex": "15f87902e42eb9232f3e2f360000",
   "zh_hex": "15e83ae7b8efb6e867ef2ae7ebeae7ef28e7f6e7f6e9190000"
  },
  {
   "jp_offset": "0x5f09",
   "jp_len": 36,
   "kind": "dialogue",
   "speaker": "玛琉",
   "jp_text": "…では、「SDガンダム{00}{01}{01}{01}{01}{01}GジェネレーシユンDS」",
   "zh_text": "……那么、就请继续游玩『SD高达G世{00}代DS』吧",
   "jp_hex": "1509f00a02e00b1411f041f048000101010101e020f9786f83085fe073851114e00c0000",
   "zh_hex": "150909e7b7e7bd02e7c5e83ae9d6e9adea94e9700cef9eef96e812ef2beed1e83c00e8e7ef96ef9e0de7d00000"
  },
  {
   "jp_offset": "0x5f2d",
   "jp_len": 28,
   "kind": "dialogue",
   "speaker": "玛琉",
   "jp_text": "『フリーバトルの戦火！{00}{01}駆け抜けろ、アークエンジェル！！』",
   "zh_text": "『自由对战的战火！尽情冲杀吧、大天使{00}号！！』",
   "jp_hex": "150cf33071f3cd37f607060001ff38f4314a02f093f09a06060d0000",
   "zh_hex": "150cefb5e8a6e7beef28e7b4ef28e8daef97e8f2e88be95ee89be7d002efa5e844e83f00e833ef97ef970d000000000000"
  },
  {
   "jp_offset": "0x5fae",
   "jp_len": 16,
   "kind": "dialogue",
   "speaker": "娜塔尔·巴吉路",
   "jp_text": "ドミニオン艦長{00}ナタル·バジルール中佐だ",
   "zh_text": "我是主天使号的舰长、娜塔尔·巴基露露{00}中佐",
   "jp_hex": "15f165f03400f19404f15af0a02b0000",
   "zh_hex": "15efcce7b6e954e844e83fe833e7b4e7d4ef3402e7eae945e7e1ef4be85be829e858e85800ef4eefba000000"
  },
  {
   "jp_offset": "0x5fbe",
   "jp_len": 34,
   "kind": "dialogue",
   "speaker": "娜塔尔·巴吉路",
   "jp_text": "まずは、ここまでの貴君の{00}見事な采配に敬意を表したい",
   "zh_text": "首先、请允许我向你一路以来出色的指挥{00}、致以由衷的敬意",
   "jp_hex": "15f15b3802f03ef02b3794973700f2a333e257e4c034e1c3e0924ce4fe232a170000",
   "zh_hex": "15ef40ef8b02e83aecade8a7efccefc1e7b8efb6e8d2e7f3efcfefbee89fe7b4e8c0e9490002ea32e7f3e8a6edb3e7b4ee38ef3c000000000000"
  },
  {
   "jp_offset": "0x5fe0",
   "jp_len": 34,
   "kind": "dialogue",
   "speaker": "娜塔尔·巴吉路",
   "jp_text": "貴君の叫力により、ついに我々は{00}最後まで戦い抜くことができた",
   "zh_text": "正是多亏了你的协助、我们才终于得以奋{00}战到最后",
   "jp_hex": "15949737f13a34f02d02f0ab34f0183800f145f02bb917e4d31ef0021cf0172a0000",
   "zh_hex": "15ef3be7b6e7e9eab7e7bae7b8e7b4e8f6ea2302efcce7bbe836e8e2e879e80ae7f3ef4600ef28e7d7e8c5e7fe000000"
  },
  {
   "jp_offset": "0x6002",
   "jp_len": 22,
   "kind": "dialogue",
   "speaker": "娜塔尔·巴吉路",
   "jp_text": "この「ライバル·ルート」は{00}ここで終了だ",
   "zh_text": "这条『对手路线』、就到此结束了",
   "jp_hex": "15f005e00bfc0f04fb35e00c3800f03e30f3ae2b0000",
   "zh_hex": "15e7b9e9d40ce7beef66e8d2e9160d02e7c5e7d7e7cae868e895e7ba000000"
  },
  {
   "jp_offset": "0x6018",
   "jp_len": 25,
   "kind": "dialogue",
   "speaker": "娜塔尔·巴吉路",
   "jp_text": "もっとも、我々ドミニオン隊の戦いは{00}ここで終了したが……",
   "zh_text": "虽说、我们主天使队的这场战斗、是已经{00}到此结束了……",
   "jp_hex": "15f39a02f018f165bd37b9173800f03e30f3aef55b09090000",
   "zh_hex": "15e8b8e7ed02efcce7bbe954e844e83fe7c9e7b4e7b9e876ef28e7ff02e7b6ef3ae8b700e7d7e7cae868e895e7ba090900000000"
  },
  {
   "jp_offset": "0x6031",
   "jp_len": 36,
   "kind": "dialogue",
   "speaker": "娜塔尔·巴吉路",
   "jp_text": "ケーム自体はまだ続けることが可能だ{00}この後も引き続き楽しんで雷しい",
   "zh_text": "不过游戏本身仍可继续下去、今后也请你{00}继续尽情游玩",
   "jp_hex": "15f763f702f0ea2bf13048f0021cf1692b00f0059c41f429e3d01df5d64d30f252170000",
   "zh_hex": "15e7b5ef36ea94ea3eefa6e88deab9e7c4e9d6e9adef4de7eb02efb9e7fee7c0e83ae7b800e9d6e9ade8f2e88bea94e970000000"
  },
  {
   "jp_offset": "0x6055",
   "jp_len": 43,
   "kind": "dialogue",
   "speaker": "娜塔尔·巴吉路",
   "jp_text": "フリーバトルはこの後も続けられるし、{00}また、「特別演習」を選ぶことで…",
   "zh_text": "自由对战今后仍可继续下去、另外、只要{00}选择『特别演习』……",
   "jp_hex": "15f33071f3cd38f0059c41f130464948230200f09e02e00be490e534f472e00c4ce39ae05af00230090000",
   "zh_hex": "15efb5e8a6e7beef28efb9e7feeab9e7c4e9d6e9adef4de7eb02e99be8f702ef32ef2a00e966eaaa0ce7cfe7e5ea2feab60d0909000000000000"
  },
  {
   "jp_offset": "0x6080",
   "jp_len": 30,
   "kind": "dialogue",
   "speaker": "娜塔尔·巴吉路",
   "jp_text": "ロンド·ベル、プリベンターとの{00}合同演習を行うこともできる",
   "zh_text": "便能与隆德·贝尔、预防者一同进行一场{00}联合演习",
   "jp_hex": "15f17a04f0f402f2b7f2d1313700a0e489f4724c9f18f00241f017480000",
   "zh_hex": "15e8fae7c6e832ed16e82cef4be857e7e102ea5ae968ef6eefb6e85de892efd6efb6e87600ef2eefc0ea2feab6000000"
  },
  {
   "jp_offset": "0x609e",
   "jp_len": 37,
   "kind": "dialogue",
   "speaker": "娜塔尔·巴吉路",
   "jp_text": "貴君ならばきっと、彼らとの戦いにも{00}勝離をおさめられると私は信じている",
   "zh_text": "我坚信、以你的本领、在与他们的战斗中{00}也定能克敌制胜",
   "jp_hex": "159497334639f31002f0d53137b917344100f25b4c1a224046494831a838f1032f17480000",
   "zh_hex": "15efcceb80e90f02e7f3e7b8e7b4efa6ea2002ef29e832e80ce7bbe7b4ef28e7ffef4e00e7c0e867e7c6e7d5e7e3e8dee8db00000000"
  },
  {
   "jp_offset": "0x60c3",
   "jp_len": 36,
   "kind": "dialogue",
   "speaker": "娜塔尔·巴吉路",
   "jp_text": "…では、「SDガンダム{00}{01}{01}{01}{01}{01}GジェネレーシユンDS」",
   "zh_text": "……那么、就请继续游玩『SD高达G世{00}代DS』吧",
   "jp_hex": "1509f00a02e00b1411f041f048000101010101e020f9786f83085fe073851114e00c0000",
   "zh_hex": "150909e7b7e7bd02e7c5e83ae9d6e9adea94e9700cef9eef96e812ef2beed1e83c00e8e7ef96ef9e0de7d00000"
  },
  {
   "jp_offset": "0x60e7",
   "jp_len": 16,
   "kind": "dialogue",
   "speaker": "娜塔尔·巴吉路",
   "jp_text": "この後も貴君の健闘を祈る",
   "zh_text": "今后也愿你武运长久、奋战不息",
   "jp_hex": "15f0059c41949737f68a4ce152480000",
   "zh_hex": "15efb9e7fee7c0e961e7b8e8ece986ef34e9db02ef46ef28e7b5ec6a000000"
  }
 ]
}
