{
 "cid": 51,
 "kind": "char_bio",
 "web_sources": [
  "https://wiki.biligame.com/gundam/GX-9900%E9%AB%98%E8%BE%BEX",
  "https://zh.moegirl.org.cn/%E6%9C%BA%E5%8A%A8%E6%96%B0%E4%B8%96%E7%BA%AA%E9%AB%98%E8%BE%BEX",
  "https://baike.baidu.com/item/%E6%9C%BA%E5%8A%A8%E6%96%B0%E4%B8%96%E7%BA%AA%E9%AB%98%E8%BE%BEX/7823628"
 ],
 "paragraphs": [
  "「月亮……看见了！」",
  "在蒂法的协助之下、加洛德如今已能自如地运用高达X的卫星炮。"
 ],
 "notes": "cid51为掌握卫星炮后的加洛德变体条目（ID技『アナタに力を……』卫星展开）、JP与cid50不同、已按本条JP独立翻译。锁定名照terms.md：ガロード→加洛德（加洛德·兰）、ティファ→蒂法（蒂法·亚迪尔、JP仅称名）、ガンダムX→高达X、サテライトキャノン→卫星炮。引言「月が……見えた！」即高达X第34话标题名场面（卫星炮启动台词）、此处无战斗吐槽的9字节预算、译作「月亮……看见了！」保留原句省略号停顿；同句bark因预算压缩为看见月亮！（见char_50 notes）。设定（蒂法以NT能力协助向月球基地注册脑波、其后加洛德可自由使用卫星炮）经biligame GX-9900页核对。无新增术语。"
}
