{
 "cid": 191,
 "kind": "char_bio",
 "web_sources": [
  "https://wiki.biligame.com/gundam/%E5%B8%83%E9%9B%B7%E5%85%8B%E6%96%AF%C2%B7%E5%BC%97%E6%8B%89",
  "https://gundam.fandom.com/wiki/Blex_Forer",
  "https://dic.pixiv.net/a/%E3%83%96%E3%83%AC%E3%83%83%E3%82%AF%E3%82%B9%E3%83%BB%E3%83%95%E3%82%A9%E3%83%BC%E3%83%A9"
 ],
 "paragraphs": [
  "「奥古的指挥、就由你来执掌……夏亚·阿兹纳布尔……」",
  "地球联邦政府的议会议员、同时也是奥古的作战指挥官、军衔为准将。因对企图镇压宇宙居民的联邦政府心怀疑虑、遂投身奥古。",
  "他甚至会亲自登上阿伽玛坐镇、虽是联邦军人却颇富行动力。不过在原作中、他并未被描绘成多么干练的指挥官……。后来他遭提坦斯暗杀、弥留之际将奥古托付给了夏亚。"
 ],
 "notes": "锁定术语沿用 terms.md：布雷克斯（ブレックス、全名按定稿作布雷克斯·弗拉、正文JP未出现姓名故未增写）、奥古（エゥーゴ）、提坦斯（ティターンズ）、阿伽玛（アーガマ）、夏亚（シャア）；引用句为全名场合、按 owner 定稿写作夏亚·阿兹纳布尔（他临终点破克瓦特罗的真实身份并托付奥古、见 biligame/pixiv 条目）。JP『地球連邦政府請会請員』中的『請』为游戏字库对『議』的替字（即議会議員）、按其本义译作议会议员。スペースノイド＝宇宙居民、沿 data/zh/event_text.json 及舞台舰队既定用法。"
}
