{
 "utid": 25,
 "kind": "unit_bio",
 "web_sources": [
  "https://wiki.biligame.com/gundam/RX-78GP03D%E9%AB%98%E8%BE%BE%E8%AF%95%E4%BD%9C3%E5%8F%B7%E6%9C%BA%EF%BC%88%E7%9F%B3%E6%96%9B%E5%85%B0%EF%BC%89",
  "https://baike.baidu.com/item/GP03D%E7%9F%B3%E6%96%9B%E5%85%B0/6001405",
  "https://gundam.fandom.com/wiki/RX-78GP03_Gundam_%22Dendrobium%22"
 ],
 "paragraphs": [
  "依据「高达开发计划」开发的试作型高达3号机。本机由作为核心单元的MS「雄蕊」与集各种兵装、推进器于一体的「奥基斯」组合构成、其战斗能力足以匹敌1个MS大队。"
 ],
 "notes": "本条为GP03石斛兰（utid25、RX-78GP03D、0083高达试作3号机、terms.md锁定显示名、正文未出现デンドロビウム故石斛兰不入正文）。terms.md锁定沿用：ステイメン=雄蕊（循锁定条目GP03{01}ステイメン=GP03雄蕊的基础名形、staging/out/units/unit_22同判、JP带「」故保留引号）。settled沿用：「ガンダム開発計画」=「高达开发计划」（unit_16/unit_19/unit_112/char_26/char_512既定、JP带「」故保留引号、系计划名非台词、循unit_16/19先例不拆引言段）、試作型ガンダムn号機=试作型高达n号机（unit_19试作型高达2号机同式、半角数字照JP保留、含MS1個大隊=1个MS大队）、コアユニット=核心单元（unit_385既定、data/zh/files/library/unit_bios.json本条v1.1亦作核心单元）、スラスター/推進器=推进器（fleet通例）、大隊=大队（char_109小岛大队先例）、兵装=兵装（unit_31/343/352等fleet通例）；JP兵装·推進器的・在正文以、顿号衔接。新报备术语：オーキス=奥基斯（Orchis、GP03的大型武器库/兵装集合体部分、biligame高达wiki及gundam.fandom中文社区通行音译、terms.md无此条、建议收入词表）。lore经biligame/baike/fandom核实：GP03D由核心MS雄蕊（Stamen）与巨型武器平台奥基斯（Orchis、集导弹荚舱·MEGA光束炮·爆导索等各式兵装与大推力推进器于一体）对接构成、火力足以单机匹敌一个MS大队——与JP文意一致、未增补JP所无设定。段落=JP无{00}々分页共1节、输出1段、flat prose无手动换行无标记；共78字、为JP 106字（strip_marks计入续行·）的74%、在45至115%窗内（aim 60至100%达标）。"
}
