{
 "chunk": 59,
 "slots": [
  {
   "slot": 1154,
   "claimed": "組",
   "contexts": [
    {
     "where": "bark 0.bin@0x25850",
     "surface": "stage",
     "decoded": "私に【組】する最後の機会を。与えてやろう！"
    },
    {
     "where": "bark 1de.bin@0x5CAC",
     "surface": "stage",
     "decoded": "いいだろう、少年！。ここは手を【組】むべき時だ！！"
    },
    {
     "where": "bark 1de.bin@0x63CC",
     "surface": "stage",
     "decoded": "ふん……まさか貴様と。手を【組】むことになろうとはな！！"
    }
   ]
  },
  {
   "slot": 1156,
   "claimed": "阻",
   "contexts": [
    {
     "where": "bark 0.bin@0x1D0B4",
     "surface": "stage",
     "decoded": "……ここで【阻】止する！"
    },
    {
     "where": "bark 0.bin@0x1D0EC",
     "surface": "stage",
     "decoded": "……ここで【阻】止する！"
    },
    {
     "where": "bark 1de.bin@0x7528",
     "surface": "stage",
     "decoded": "何としても【阻】止するのよ！！"
    }
   ]
  },
  {
   "slot": 1158,
   "claimed": "創",
   "contexts": [
    {
     "where": "bark 0.bin@0x8FDC",
     "surface": "stage",
     "decoded": "私は貴族主義社会を【創】るのだよ！"
    }
   ]
  },
  {
   "slot": 1164,
   "claimed": "想",
   "contexts": [
    {
     "where": "bark 0.bin@0x68A8",
     "surface": "stage",
     "decoded": "【想】いだけじゃない……！"
    },
    {
     "where": "bark 0.bin@0x9298",
     "surface": "stage",
     "decoded": "予【想】外の事は起こるもの……"
    },
    {
     "where": "bark 0.bin@0x92B0",
     "surface": "stage",
     "decoded": "予【想】外の事は。起こるもの……"
    }
   ]
  },
  {
   "slot": 1166,
   "claimed": "掃",
   "contexts": [
    {
     "where": "bark 0.bin@0x259B4",
     "surface": "stage",
     "decoded": "反乱分子を一【掃】せよ！"
    },
    {
     "where": "bark 0.bin@0x258D1",
     "surface": "stage",
     "decoded": "よし……。反乱分子を一【掃】しろ！"
    },
    {
     "where": "bark 0.bin@0x269BE",
     "surface": "stage",
     "decoded": "よし！。反乱分子どもを一【掃】しろ！！"
    }
   ]
  },
  {
   "slot": 1167,
   "claimed": "操",
   "contexts": [
    {
     "where": "bark 0.bin@0x2EA1C",
     "surface": "stage",
     "decoded": "チッ……。【操】作をミスったのか！？"
    },
    {
     "where": "bark 0.bin@0x145F0",
     "surface": "stage",
     "decoded": "【操】艦そのままっ！。NAVCOMにデータ転送！"
    },
    {
     "where": "bark 0.bin@0x148A0",
     "surface": "stage",
     "decoded": "【操】艦そのままっ！。NAVCOMにデータ転送！"
    }
   ]
  },
  {
   "slot": 1168,
   "claimed": "早",
   "contexts": [
    {
     "where": "bark 0.bin@0x25288",
     "surface": "stage",
     "decoded": "来たぞ！。【早】く迎え撃たんか！！"
    },
    {
     "where": "bark 0.bin@0x4644",
     "surface": "stage",
     "decoded": "【早】く終わらせたいんだ！。こんな戦争はッ！"
    },
    {
     "where": "bark 0.bin@0x48B4",
     "surface": "stage",
     "decoded": "【早】く終わらせたいんだ！。こんな戦争はッ！"
    }
   ]
  },
  {
   "slot": 1169,
   "claimed": "曹",
   "contexts": [
    {
     "where": "bark 0.bin@0x72FE",
     "surface": "stage",
     "decoded": "御【曹】司！。無青任な事は言わんでいただきたい！"
    },
    {
     "where": "bark 0.bin@0x7340",
     "surface": "stage",
     "decoded": "今は戦闘中です！。御【曹】司は黙っていてください！！"
    },
    {
     "where": "bark 0.bin@0x71F5",
     "surface": "stage",
     "decoded": "御【曹】司！戦闘の指揮は。私に一任していただきたい！！"
    }
   ]
  },
  {
   "slot": 1171,
   "claimed": "争",
   "contexts": [
    {
     "where": "bark 0.bin@0x3070",
     "surface": "stage",
     "decoded": "あたしは、戦【争】やってんのよ！"
    },
    {
     "where": "bark 0.bin@0x45C0",
     "surface": "stage",
     "decoded": "あきらめな！。あんたの戦【争】は終わったのさ！"
    },
    {
     "where": "bark 0.bin@0x4644",
     "surface": "stage",
     "decoded": "早く終わらせたいんだ！。こんな戦【争】はッ！"
    }
   ]
  },
  {
   "slot": 1172,
   "claimed": "相",
   "contexts": [
    {
     "where": "bark 0.bin@0xAAC8",
     "surface": "stage",
     "decoded": "貴様の【相】手は俺だ……！"
    },
    {
     "where": "bark 0.bin@0x2964",
     "surface": "stage",
     "decoded": "くっ……！。これほどの【相】手とは！"
    },
    {
     "where": "bark 0.bin@0x232C",
     "surface": "stage",
     "decoded": "この程度の【相】手なら楽なもんだ！"
    }
   ]
  }
 ]
}