{
 "entity": "char_438",
 "web_sources": [
  "https://gundam.huijiwiki.com/wiki/%E6%A0%BC%E9%9B%B7%E7%B1%B3%E5%86%9B",
  "https://gundam.fandom.com/wiki/Glemy_Toto",
  "https://dic.pixiv.net/a/%CE%BD%E3%82%AC%E3%83%B3%E3%83%80%E3%83%A0%E3%81%AF%E4%BC%8A%E9%81%94%E3%81%98%E3%82%83%E3%81%AA%E3%81%84"
 ],
 "name_flag": "",
 "ids": [
  {
   "idn": 1314,
   "name_zh": "只要立战功",
   "cutin_zh": "只要立下战功、接下来就好办了！",
   "notes": "手柄さえたてちまえばこっちのもんだ！与char_437杂兵bark为同一句、按其定稿的手柄=立战功译法对齐（こっちのもんだ=接下来就好办了）。指令名保留5格的只要立战功、与名台词共享核心词。效果文本归char_410、不输出。"
  }
 ],
 "barks": [
  {"file": "0.bin", "record": "0x30E1C", "zh": "蠢货！竟自己送上门来！！"},
  {"file": "0.bin", "record": "0x30E40", "zh": "就拿你刷战绩！！"},
  {"file": "0.bin", "record": "0x30E5C", "zh": "就拿你刷战绩！！"},
  {"file": "0.bin", "record": "0x30E78", "zh": "休想阻挡！！"},
  {"file": "0.bin", "record": "0x30E90", "zh": "击落你就能换赏金！"},
  {"file": "0.bin", "record": "0x30EB0", "zh": "为我的前程去死吧！"},
  {"file": "0.bin", "record": "0x30ED0", "zh": "休想抵抗！！"},
  {"file": "0.bin", "record": "0x30EE8", "zh": "真碍眼！！"},
  {"file": "0.bin", "record": "0x30EFC", "zh": "不可能……！？为何是我……啊啊！！"},
  {"file": "0.bin", "record": "0x30F24", "zh": "哼……真可笑！"},
  {"file": "0.bin", "record": "0x30F3C", "zh": "只要活到最后！！"},
  {"file": "0.bin", "record": "0x30F58", "zh": "哼、真可笑！"},
  {"file": "0.bin", "record": "0x30F70", "zh": "唔！……真有两下子！"},
  {"file": "0.bin", "record": "0x30F90", "zh": "绝不放过你！！"},
  {"file": "0.bin", "record": "0x30FA8", "zh": "这、这力量……太悬殊了！！"},
  {"file": "0.bin", "record": "0x30FCC", "zh": "什么！难道……被压制了！？"},
  {"file": "0.bin", "record": "0x30FF0", "zh": "不是摆设！！"},
  {"file": "0.bin", "record": "0x31008", "zh": "这招吗……哼！"},
  {"file": "0.bin", "record": "0x31020", "zh": "回避！各机、散开！！"},
  {"file": "0.bin", "record": "0x3103C", "zh": "把那机体带回去也是战功！"},
  {"file": "0.bin", "record": "0x31060", "zh": "什么！？竟被俘……"},
  {"file": "0.bin", "record": "0x3107C", "zh": "专程来送死！"}
 ],
 "notes": "格雷米军精锐兵：与char_431/432/437同派系语音组、统一走战功／赏金／前程的功利精锐口吻（手柄=战功、出世=前程、スコア=刷战绩）。修正两处误译：0x30F24/0x30F58笑わせるな原译别挡路、改为真可笑；0x30ED0删去原译多出的第三个！。0x30FF0ダテじゃないんだよ对齐社区通行的伊達じゃない=不是摆设。0x3107C原译特意来送死吗超预算、改专程来送死（11字节）；0x31020原译按公式超预算、改回避！各机、散开！！（16字节）。0x30EFC预算26放不下ば、馬鹿な的结巴、取不可能……！？为何是我……啊啊！！（26字节整）。0x31060被抓改军语被俘、与char_432用词一致。"
}
