{
 "entity": "char_197",
 "web_sources": [
  "https://wiki.biligame.com/gundam/%E9%A9%AC%E9%9B%85%C2%B7%E6%B3%95%E6%8B%89%E5%A5%A5",
  "https://zh.moegirl.org.cn/%E6%9C%BA%E5%8A%A8%E6%88%98%E5%A3%ABZ%E9%AB%98%E8%BE%BE",
  "https://nikenickel.com/archives/510",
  "https://datenoba.exblog.jp/31619318/",
  "https://gundam.wiki.cre.jp/wiki/%E3%83%9E%E3%82%A6%E3%82%A2%E3%83%BC%E3%83%BB%E3%83%95%E3%82%A1%E3%83%A9%E3%82%AA",
  "https://bangumi.tv/character/31598"
 ],
 "name_flag": "",
 "ids": [
  {
   "idn": 591,
   "name_zh": "说过守护你",
   "cutin_zh": "我说过会守护你的吧？",
   "detail_effect_zh": "攻击力增加20%。替队伍承受所有攻击、伤害减至1／4",
   "notes": "Z第30话捷利特特攻名场面、玛雅替捷利特挡下Z高达的致命一击时的遗言（原句守ってみせるって言ったろ…ジェリド？、nikenickel/datenoba）。detail原为空、已补全；JP引き愛ける为引き受ける之转录讹字；1／4全角斜杠与char_50/char_122同类措辞统一。"
  },
  {
   "idn": 592,
   "name_zh": "凭个人感情",
   "cutin_zh": "现在的你是在凭个人感情行事、那样是无法出人头地的",
   "detail_effect_zh": "回避率提升40%、装甲增加4",
   "notes": "Z第24话冯·布朗、玛雅规劝捷利特勿以私怨行事之名言（それでは上は狙えない、gundam.wiki.cre.jp/nikenickel）。detail旧译混入了机械拼接的使用条件前缀、按简报只译效果子句。"
  },
  {
   "idn": 593,
   "name_zh": "现在这才对",
   "cutin_zh": "活下去、战斗下去……对现在的你来说、这才是正确的……",
   "detail_effect_zh": "捷利特在队伍中时、HP回复50%",
   "notes": "Z第30话玛雅濒死时对捷利特的临终之言（生き延びること…戦うこと…あなたにとって今はそれが正しい…、nikenickel）。detail原为空、已补全；与char_82的玛雅在队条件指令相对成对。"
  }
 ],
 "barks": [
  {"file": "0.bin", "record": "0x1A500", "zh": "既然你这样……！！"},
  {"file": "0.bin", "record": "0x1A51C", "zh": "感觉……那里！"},
  {"file": "0.bin", "record": "0x1A534", "zh": "我会守护捷利特！"},
  {"file": "0.bin", "record": "0x1A550", "zh": "战斗中犹豫就输！"},
  {"file": "0.bin", "record": "0x1A56C", "zh": "休想妨碍他！！"},
  {"file": "0.bin", "record": "0x1A588", "zh": "我有……必须守护的人！"},
  {"file": "0.bin", "record": "0x1A5AC", "zh": "到此为止！"},
  {"file": "0.bin", "record": "0x1A5C4", "zh": "决心做他的后盾……所以！！"},
  {"file": "0.bin", "record": "0x1A5E8", "zh": "……捷利特……没能守护你……"},
  {"file": "0.bin", "record": "0x1A60C", "zh": "这种程度！"},
  {"file": "0.bin", "record": "0x1A624", "zh": "我还不能死！"},
  {"file": "0.bin", "record": "0x1A640", "zh": "……不算什么"},
  {"file": "0.bin", "record": "0x1A658", "zh": "不错！可是！！"},
  {"file": "0.bin", "record": "0x1A670", "zh": "我大意了……"},
  {"file": "0.bin", "record": "0x1A688", "zh": "不好！捷利特、小心！！"},
  {"file": "0.bin", "record": "0x1A6A8", "zh": "还没……！还不能倒下……！！"},
  {"file": "0.bin", "record": "0x1A6CC", "zh": "住手！没用的！！"},
  {"file": "0.bin", "record": "0x1A6E8", "zh": "不能中这招！！"},
  {"file": "0.bin", "record": "0x1A700", "zh": "来了！散开！"},
  {"file": "0.bin", "record": "0x1A718", "zh": "抵抗没用、投降吧！"},
  {"file": "0.bin", "record": "0x1A738", "zh": "捷利特！"},
  {"file": "0.bin", "record": "0x1A74C", "zh": "不能被抓！！"},
  {"file": "1de.bin", "record": "0x69A8", "zh": "全员一起上！配合好时机！"},
  {"file": "1de.bin", "record": "0x69C8", "zh": "……掩护！"},
  {"file": "1de.bin", "record": "0x69DC", "zh": "捷利特！我随时能上！"},
  {"file": "1de.bin", "record": "0x69FC", "zh": "……掩护！"},
  {"file": "1de.bin", "record": "0x6A10", "zh": "……掩护！"},
  {"file": "1de.bin", "record": "0x6A24", "zh": "……掩护！"},
  {"file": "1de.bin", "record": "0x6A38", "zh": "……掩护！"}
 ],
 "notes": "玛雅·法拉奥=提坦斯女驾驶员、捷利特的恋人搭档、冯·布朗战役中为救捷利特而死（biligame/萌百）；口吻取冷静温柔、对捷利特深情克制。与char_82对齐：马乌阿=玛雅、捷利特称呼一致、0x69DC我随时能上与其idn251玛雅……可以上了！！成对。bark修复：0x1A56C原三个叹号改回JP的两个；0x1A5C4补回JP的！！收尾（22/23）；0x1A5E8按JP恢复首尾省略号与守护措辞（恰22/22）；0x1A688补回、与！！（恰18/18、この敵は只能以小心示警）；0x1A6A8恢复JP的……！/……！！节奏（21/22）；0x1A6E8これには当たれない为闪避语、改译不能中这招（原译这个打不中系反向理解）；0x1A624去掉JP没有的第二个叹号。0x1A738预算7放不下……捷利特……（8）、保留现行捷利特！、理想版记此。0x1A700与0x69A8按编码器实测已在预算内（8/9、18/18）、原样保留不动。biligame条目题名用马雅、bangumi等用玛雅、属音译变体、与库内定名玛雅·法拉奥不冲突、故不设name_flag。"
}
