{
 "entity": "unit_130",
 "web_sources": [
  "https://wiki.biligame.com/gundam/GAT-X131%E7%81%BE%E5%8E%84%E9%AB%98%E8%BE%BE",
  "https://wiki.biligame.com/gundam/%E5%9C%A3%E7%9B%BE%E9%AB%98%E8%BE%BE",
  "https://baike.baidu.com/item/%E7%81%BE%E9%9A%BE%E9%AB%98%E8%BE%BE/739895"
 ],
 "name_zh": "灾厄高达",
 "weapons": [
  {"slot": 0, "zh": "亡者之路火箭炮"}
 ],
 "defense_name_zh": "",
 "defense_segments_zh": [
  "威力900以下的实弹属性攻击无效"
 ],
 "notes": "机体名灾厄高达与仓库标签及biligame页标题GAT-X131灾厄高达一致、保留。slot0トーデスブロック(Todesblock、337mm电浆穿甲火箭炮)现译死亡块为机翻式直译缺陷、按biligame机体页通行译名亡者之路改为亡者之路火箭炮(仿本机斯库拉加农炮/舒拉克加农炮的昵称+炮种house style；该串仅灾厄3个utid共享、改动安全)。slot2スキュラ保留斯库拉加农炮：biligame正文虽用海妖魔兽、但同页明注即斯库拉(Scylla)、且该串与圣盾高达6个utid共享、音译不属canon错误。slot3シュラーク保留舒拉克加农炮：biligame将Schlag记作冲角、与甲虫二式的冲角炮描述冲突易混淆、音译舒拉克为模型/社区常用、非canon错误。slot1甲虫二式与biligame完全一致。防御名TP装甲为canon(TransPhase装甲、受实弹冲击瞬时启动PS装甲)、保留。防御说明按brief要求1:1镜像jp_segments合并为单段、开头保持威力900数字版式、16字≈32字节≤36字节预算；旧译拆成两段且漏译属性二字。驾驶员奥尔加·萨布纳克、与char_31产出一致。"
}
